{
  "ComponentIndexes": {
    "HorizontalMenuComponent": 8,
    "ProgressBar": 9
  },
  "ControlUniqueGuids": {},
  "ControlUniqueIds": {
    "Actual ETA_DataCard1": 239,
    "Actual ETD_DataCard1": 229,
    "ActualETA_TD_6": 98,
    "ActualETD_TD_6": 97,
    "App": 1,
    "Approved Cases_DataCard1": 285,
    "AttachmentControl_2": 479,
    "AttachmentControl_4": 415,
    "BL#_DataCard1": 259,
    "BLNo_TD_6": 102,
    "BU Comment_DataCard1": 300,
    "button_approve": 338,
    "Button_CancelGoBack": 339,
    "Button_CancelGoBack_2": 350,
    "Button_CIN_TD_3": 108,
    "Button_delete": 337,
    "button_gallery_cin_2": 501,
    "button_gallery_cin_4": 387,
    "button_gallery_cin_5": 447,
    "button_process": 341,
    "Button_reject": 340,
    "Button_reject_2": 349,
    "button_Submit": 336,
    "Button2_2": 481,
    "Button2_4": 419,
    "Button5": 10,
    "CancelUpload": 328,
    "Canvas2_1": 371,
    "cbKPI_ClaimType": 368,
    "cbKPI_Market": 369,
    "cbKPI_Period": 370,
    "CIN (Title)_DataCard1": 177,
    "Claim Status_DataCard1": 214,
    "Claim Type_DataCard1": 234,
    "claim_draft_screen": 52,
    "ClaimForm": 176,
    "ClaimSubDate_TD_6": 106,
    "ClaimType_TD_6": 109,
    "ColumnChart1": 526,
    "ColumnChart2_2": 420,
    "combo_ct_2": 486,
    "combo_ct_7": 410,
    "combo_ct_8": 427,
    "combo_market_3": 412,
    "combo_status_2": 487,
    "combo_status_6": 411,
    "combo_status_7": 428,
    "CompositeColumnChart1": 532,
    "CompositeLineChart1": 533,
    "CompositePieChart1": 534,
    "cont_Attachment": 167,
    "cont_ClaimDetail": 126,
    "cont_PopupGrey": 127,
    "Container #_DataCard1": 254,
    "Container1": 364,
    "Container1_2": 476,
    "Container1_5": 406,
    "Container1_8": 63,
    "Container2": 47,
    "Container3": 48,
    "Container4": 429,
    "Container5": 49,
    "Container7_1": 430,
    "ContainerErrorETA": 139,
    "ContainerErrorKelloggPO": 131,
    "ContainerErrorSSCC": 136,
    "ContainerNo_TD_6": 101,
    "CusReqETA_TD_6": 96,
    "Customer Comment_DataCard1": 295,
    "Customer PO_DataCard1": 182,
    "Customer Requested ETA_DataCard1": 224,
    "CustomerPO_TD_6": 90,
    "dashboard_btn_10": 358,
    "dashboard_btn_11": 56,
    "dashboard_btn_3": 470,
    "dashboard_btn_5": 400,
    "dashboard_btn_7": 120,
    "DataCard2_1": 372,
    "DataCardKey1": 179,
    "DataCardKey10": 226,
    "DataCardKey11": 231,
    "DataCardKey12": 241,
    "DataCardKey13": 246,
    "DataCardKey14": 251,
    "DataCardKey15": 256,
    "DataCardKey16": 261,
    "DataCardKey17": 266,
    "DataCardKey18": 282,
    "DataCardKey19": 277,
    "DataCardKey2": 200,
    "DataCardKey20": 216,
    "DataCardKey21": 287,
    "DataCardKey22": 297,
    "DataCardKey23": 302,
    "DataCardKey24": 307,
    "DataCardKey25": 312,
    "DataCardKey26": 317,
    "DataCardKey27": 272,
    "DataCardKey28": 292,
    "DataCardKey3": 236,
    "DataCardKey4": 184,
    "DataCardKey5": 189,
    "DataCardKey6": 194,
    "DataCardKey7": 206,
    "DataCardKey8": 211,
    "DataCardKey9": 221,
    "DataCardValue1": 180,
    "DataCardValue10": 227,
    "DataCardValue11": 232,
    "DataCardValue12": 242,
    "DataCardValue13": 247,
    "DataCardValue14": 252,
    "DataCardValue15": 257,
    "DataCardValue16": 262,
    "DataCardValue17": 268,
    "DataCardValue18": 283,
    "DataCardValue19": 278,
    "DataCardValue2": 202,
    "DataCardValue20": 217,
    "DataCardValue21": 288,
    "DataCardValue22": 298,
    "DataCardValue23": 303,
    "DataCardValue24": 308,
    "DataCardValue25": 313,
    "DataCardValue26": 318,
    "DataCardValue27": 273,
    "DataCardValue28": 293,
    "DataCardValue3": 237,
    "DataCardValue4": 185,
    "DataCardValue5": 190,
    "DataCardValue6": 196,
    "DataCardValue7": 207,
    "DataCardValue8": 212,
    "DataCardValue9": 222,
    "DateBU": 33,
    "DateBU_1": 162,
    "DateGBS": 37,
    "DateGBS_1": 166,
    "DateNew": 35,
    "DateNew_1": 164,
    "DatePIOFinance": 36,
    "DatePIOFinance_1": 165,
    "DatePIOSPOC": 34,
    "DatePIOSPOC_1": 163,
    "dd__2": 480,
    "dd__4": 416,
    "DDRF#_DataCard1": 275,
    "DDRF_TD_6": 105,
    "draft_btn_11": 57,
    "draft_btn_3": 471,
    "draft_btn_7": 118,
    "draft_btn_9": 356,
    "draftclaimdetail_screen": 114,
    "ErrorETA": 141,
    "ErrorKelloggPO": 133,
    "ErrorMessage1": 181,
    "ErrorMessage10": 228,
    "ErrorMessage11": 233,
    "ErrorMessage12": 243,
    "ErrorMessage13": 248,
    "ErrorMessage14": 253,
    "ErrorMessage15": 258,
    "ErrorMessage16": 263,
    "ErrorMessage17": 269,
    "ErrorMessage18": 284,
    "ErrorMessage19": 279,
    "ErrorMessage2": 304,
    "ErrorMessage20": 218,
    "ErrorMessage21": 289,
    "ErrorMessage22": 299,
    "ErrorMessage23": 309,
    "ErrorMessage24": 314,
    "ErrorMessage25": 319,
    "ErrorMessage26": 274,
    "ErrorMessage27": 294,
    "ErrorMessage28": 203,
    "ErrorMessage3": 238,
    "ErrorMessage4": 186,
    "ErrorMessage5": 191,
    "ErrorMessage6": 197,
    "ErrorMessage7": 208,
    "ErrorMessage8": 213,
    "ErrorMessage9": 223,
    "ErrorSSCC": 138,
    "Estimated Claim Value_DataCard1": 270,
    "ExportToExcel_button": 422,
    "FileAttachment": 170,
    "Final Claim Value_DataCard1": 290,
    "FooterContainer1": 51,
    "forgot_pswrd": 519,
    "Gallery_CreditNote": 331,
    "Gallery_DamageImage": 171,
    "Gallery_Supporting Documents": 322,
    "Gallery_WHReceipt": 142,
    "Gallery4_3": 498,
    "Gallery4_6": 444,
    "GalleryKPI": 385,
    "galleryTemplate1": 7,
    "galleryTemplate2": 9,
    "galleryTemplate3": 143,
    "galleryTemplate3_2": 172,
    "galleryTemplate3_3": 323,
    "galleryTemplate3_6": 332,
    "galleryTemplate4_3": 499,
    "galleryTemplate4_5": 386,
    "galleryTemplate4_6": 445,
    "galleryTemplate4_9": 89,
    "GBS Comment_DataCard1": 315,
    "Group1_4": 462,
    "Group3_2": 511,
    "Group3_5": 461,
    "Group4": 463,
    "Group5": 443,
    "HeaderClaimDraft_6": 67,
    "HeaderContainer1_2": 116,
    "HeaderContainer1_5": 467,
    "HeaderContainer1_6": 354,
    "HeaderContainer1_7": 397,
    "HeaderContainer1_9": 54,
    "HeaderContainer2": 44,
    "HeightSubmenu": 14,
    "HorizontalMenuComponent": 3,
    "HorizontalMenuComponent_1": 523,
    "HorizontalMenuComponent_2": 45,
    "Icon_Add_ImageDamage": 168,
    "Icon_Add_SupportingDocs": 320,
    "Icon_AddCreditNote": 329,
    "Icon_AddWHReceipt": 134,
    "Icon1_2": 510,
    "Icon1_4": 459,
    "Icon1_6": 110,
    "Icon10": 12,
    "Icon11": 13,
    "Icon2_5": 112,
    "Icon2_7": 394,
    "Icon3": 130,
    "Icon4_1": 195,
    "Icon4_2": 267,
    "Icon4_4": 201,
    "Icon5": 345,
    "Icon5_10": 362,
    "Icon5_11": 404,
    "Icon5_5": 474,
    "Icon5_6": 124,
    "Icon5_8": 61,
    "Icon6_3": 59,
    "Icon6_5": 473,
    "Icon6_6": 123,
    "Icon6_8": 361,
    "Icon6_9": 403,
    "Icon7_1": 16,
    "Icon7_2": 17,
    "Icon8": 145,
    "Icon8_1": 174,
    "Icon8_2": 325,
    "Icon8_6": 334,
    "Icon9": 146,
    "Icon9_1": 175,
    "Icon9_2": 326,
    "Icon9_6": 335,
    "IconErrorETA": 140,
    "IconErrorKelloggPO": 132,
    "IconErrorSSCC": 137,
    "Image1": 516,
    "Image2_10": 355,
    "Image2_12": 55,
    "Image2_3": 468,
    "Image2_5": 398,
    "Image2_8": 117,
    "Image3_2": 478,
    "Image3_4": 414,
    "input_search_2": 485,
    "input_search_4": 426,
    "InvDate_TD_6": 100,
    "Invoice Date_DataCard1": 249,
    "Kellogg Code_DataCard1": 204,
    "Kellogg Inv #_DataCard1": 244,
    "Kellogg PO#_DataCard1": 192,
    "Kellogg SO#_DataCard1": 187,
    "KelloggCode_TD_6": 93,
    "KelloggInvNo_TD_6": 99,
    "KelloggPO_TD_6": 92,
    "KelloggSO_TD_6": 91,
    "kpi_btn_1": 401,
    "kpi_btn_2": 121,
    "kpi_btn_5": 359,
    "kpi_screen": 352,
    "Label_ActualETA_6": 78,
    "Label_ActualETD_6": 77,
    "Label_BLNo_6": 82,
    "Label_CIN_6": 68,
    "Label_ClaimSubDate_6": 86,
    "Label_ClaimType_6": 69,
    "Label_ContainerNo_6": 81,
    "Label_CusReqETA_6": 76,
    "Label_CustomerPO_6": 70,
    "Label_DDRF_6": 85,
    "Label_InvDate_6": 80,
    "Label_KelloggCode_6": 73,
    "Label_KelloggInvNo_6": 79,
    "Label_KelloggPO_6": 72,
    "Label_KelloggSO_6": 71,
    "Label_ProductDesc_6": 74,
    "Label_Quantity_6": 75,
    "Label_SSCCNo_6": 83,
    "Label_Status_6": 87,
    "Label_TotalCases_6": 84,
    "Label1": 346,
    "Label1_27": 488,
    "Label1_28": 489,
    "Label1_29": 490,
    "Label1_30": 491,
    "Label1_31": 492,
    "Label1_32": 493,
    "Label1_33": 494,
    "Label1_34": 495,
    "Label1_35": 496,
    "Label1_42": 379,
    "Label1_43": 380,
    "Label1_44": 381,
    "Label1_45": 382,
    "Label1_46": 383,
    "Label1_47": 384,
    "Label1_84": 431,
    "Label1_85": 432,
    "Label1_86": 433,
    "Label1_87": 434,
    "Label1_88": 435,
    "Label1_89": 436,
    "Label1_90": 437,
    "Label1_91": 438,
    "Label1_92": 439,
    "Label1_93": 440,
    "Label1_94": 441,
    "Label1_95": 442,
    "Label2": 343,
    "Label3_2": 497,
    "Label3_5": 460,
    "Label4": 128,
    "Label5": 144,
    "Label5_11": 472,
    "Label5_12": 333,
    "Label5_13": 122,
    "Label5_15": 60,
    "Label5_17": 402,
    "Label5_20": 360,
    "Label5_5": 173,
    "Label5_6": 324,
    "Label6": 135,
    "Label6_1": 169,
    "Label6_2": 321,
    "Label6_6": 330,
    "Label7_4": 418,
    "Label7_5": 417,
    "Label9_6": 64,
    "landing_screen": 395,
    "landing_screen_distributor": 465,
    "lbl_ClaimType1_11": 407,
    "lbl_ClaimType1_12": 424,
    "lbl_ClaimType1_6": 483,
    "lbl_ClaimType1_8": 365,
    "lbl_ClaimType2_2": 477,
    "lbl_ClaimType2_4": 413,
    "lbl_ecv": 453,
    "lbl_faq": 452,
    "lbl_fcv": 454,
    "lbl_hdn_warnings_2": 509,
    "lbl_hdn_warnings_4": 111,
    "lbl_hdn_warnings_5": 458,
    "lbl_hdn_warnings_7": 393,
    "lbl_SearchKeyword_6": 482,
    "lbl_SearchKeyword_8": 423,
    "lbl_Status_13": 408,
    "lbl_Status_14": 409,
    "lbl_Status_15": 425,
    "lbl_Status_6": 484,
    "lbl_Status_8": 366,
    "lbl_Status_9": 367,
    "lbl_tbl_cd_2": 506,
    "lbl_tbl_cd_4": 455,
    "lbl_tbl_comments_2": 508,
    "lbl_tbl_comments_4": 457,
    "lbl_tbl_country_2": 500,
    "lbl_tbl_country_4": 388,
    "lbl_tbl_country_5": 446,
    "lbl_tbl_ct_2": 502,
    "lbl_tbl_ct_4": 389,
    "lbl_tbl_ct_5": 448,
    "lbl_tbl_in_2": 504,
    "lbl_tbl_in_4": 391,
    "lbl_tbl_in_5": 450,
    "lbl_tbl_kpo_2": 503,
    "lbl_tbl_kpo_4": 390,
    "lbl_tbl_kpo_5": 449,
    "lbl_tbl_status_2": 507,
    "lbl_tbl_status_4": 456,
    "lbl_tbl_tcfc_2": 505,
    "lbl_tbl_tcfc_4": 392,
    "lbl_tbl_tcfc_5": 451,
    "Legend3": 531,
    "LineChart1": 527,
    "LineChart2_2": 421,
    "LinkCanvas1": 535,
    "login_btn": 521,
    "login_screen": 513,
    "Logo": 5,
    "MainMenu": 6,
    "MainSectionContainer1_2": 125,
    "MainSectionContainer1_5": 475,
    "MainSectionContainer1_6": 363,
    "MainSectionContainer1_7": 405,
    "MainSectionContainer1_9": 62,
    "MainSectionContainer2": 46,
    "menu_screen": 522,
    "password_txt": 518,
    "PieChart1": 530,
    "PIOFinance Comment_DataCard1": 310,
    "PIOSPOC Comment_DataCard1": 305,
    "PopupReject": 351,
    "PowerBI1": 529,
    "PowerBI12": 373,
    "PowerBI13": 374,
    "PowerBI14": 375,
    "PowerBI15": 376,
    "PowerBI16": 377,
    "PowerBI18": 378,
    "Product Description _DataCard1": 209,
    "ProductDes_TD_6": 94,
    "Progress_Trail": 147,
    "ProgressBar": 18,
    "ProgressBar_1": 50,
    "Quantity (cs)_DataCard1": 219,
    "Quantity_TD_6": 95,
    "Rectangle1": 514,
    "Rectangle2": 515,
    "Rectangle3": 129,
    "Rectangle4": 4,
    "Rectangle5": 11,
    "Rectangle6": 464,
    "Rectangle6_10": 155,
    "Rectangle6_11": 156,
    "Rectangle6_2": 512,
    "Rectangle6_3": 113,
    "Rectangle6_4": 24,
    "Rectangle6_5": 25,
    "Rectangle6_6": 26,
    "Rectangle6_7": 27,
    "Rectangle6_8": 153,
    "Rectangle6_9": 154,
    "Rectangle7_10": 357,
    "Rectangle7_11": 58,
    "Rectangle7_3": 469,
    "Rectangle7_5": 399,
    "Rectangle7_7": 119,
    "RectangleOverlay": 342,
    "RectangleRejectReasonPopup": 344,
    "RejectReason": 347,
    "RejectReasonOthers": 348,
    "remember_cb": 520,
    "SaveDocument": 327,
    "ScreenContainer1_10": 53,
    "ScreenContainer1_2": 115,
    "ScreenContainer1_5": 466,
    "ScreenContainer1_6": 353,
    "ScreenContainer1_7": 396,
    "ScreenContainer2": 43,
    "SearchInput_6": 65,
    "SSCC#_DataCard1": 264,
    "SSCC_TD_6": 103,
    "StarVisible1": 178,
    "StarVisible10": 225,
    "StarVisible11": 230,
    "StarVisible12": 240,
    "StarVisible13": 245,
    "StarVisible14": 250,
    "StarVisible15": 255,
    "StarVisible16": 260,
    "StarVisible17": 265,
    "StarVisible18": 281,
    "StarVisible19": 276,
    "StarVisible2": 301,
    "StarVisible20": 215,
    "StarVisible21": 286,
    "StarVisible22": 296,
    "StarVisible23": 306,
    "StarVisible24": 311,
    "StarVisible25": 316,
    "StarVisible26": 271,
    "StarVisible27": 291,
    "StarVisible28": 199,
    "StarVisible3": 235,
    "StarVisible4": 183,
    "StarVisible5": 188,
    "StarVisible6": 193,
    "StarVisible7": 205,
    "StarVisible8": 210,
    "StarVisible9": 220,
    "status_screen": 42,
    "Status_TD_6": 107,
    "StatusIcon_10": 151,
    "StatusIcon_11": 152,
    "StatusIcon_2": 19,
    "StatusIcon_3": 20,
    "StatusIcon_4": 21,
    "StatusIcon_5": 22,
    "StatusIcon_6": 23,
    "StatusIcon_7": 148,
    "StatusIcon_8": 149,
    "StatusIcon_9": 150,
    "Submenu": 8,
    "Submission Date_DataCard1": 198,
    "TableClaimDraft_6": 66,
    "TableDataClaimDraft_6": 88,
    "Title1": 524,
    "Title2": 525,
    "Title3": 528,
    "Title4_10": 160,
    "Title4_11": 161,
    "Title4_2": 28,
    "Title4_3": 29,
    "Title4_4": 30,
    "Title4_5": 31,
    "Title4_6": 32,
    "Title4_7": 157,
    "Title4_8": 158,
    "Title4_9": 159,
    "Total cases for Claim_DataCard1": 280,
    "TotalCases_TD_6": 104,
    "username": 15,
    "username_txt": 517
  },
  "FunctionParamsInvariantScripts": {},
  "FunctionParamsInvariantScriptsOnInstances": {},
  "HeaderLastSavedDateTimeUTC": "04/18/2023 11:29:32",
  "IsLegacyComponentAllowGlobalScopeCase": false,
  "LocalConnectionIDReferences": {
    "1390746f-2c3e-4bd4-b54c-35d18b14ab9e": "\"/providers/microsoft.powerapps/apis/shared_sharepointonline/connections/2a12323711f144ffad14847457f657b8\"",
    "2279b649-02fe-4a89-b294-78385dbd9d71": "\"/providers/microsoft.powerapps/apis/shared_sharepointonline/connections/2a12323711f144ffad14847457f657b8\"",
    "2dbd8dad-6f1c-4c9b-9fae-345aa92406b2": "\"/providers/microsoft.powerapps/apis/shared_sharepointonline/connections/2a12323711f144ffad14847457f657b8\"",
    "5cb34b41-1110-46e1-b6ff-b8ae909da929": "\"/providers/microsoft.powerapps/apis/shared_sharepointonline/connections/2a12323711f144ffad14847457f657b8\"",
    "6d39c6b4-bf08-4f97-98e6-7bd1a95ca5a3": "\"/providers/microsoft.powerapps/apis/shared_logicflows/connections/3dd972f7ed334922bd67c6a6e86063f7\"",
    "7515b6ee-efc6-4098-8f1c-6c832a908684": "\"/providers/microsoft.powerapps/apis/shared_sharepointonline/connections/2a12323711f144ffad14847457f657b8\"",
    "8011ed01-664b-4730-9cc8-cc23dafdd925": "\"/providers/microsoft.powerapps/apis/shared_logicflows/connections/c69f708d61054732804c2be0718f9f23\"",
    "8b52b43c-d21e-4f2a-8535-a5fa79b5befe": "\"/providers/microsoft.powerapps/apis/shared_sharepointonline/connections/2a12323711f144ffad14847457f657b8\"",
    "9a7984b5-a691-4ab6-8ae0-5c6c1a24fc9d": "\"/providers/microsoft.powerapps/apis/shared_sharepointonline/connections/2a12323711f144ffad14847457f657b8\"",
    "a0209dfa-32fa-4e86-a42c-9ed2b7879ccb": "\"/providers/microsoft.powerapps/apis/shared_logicflows/connections/cea831bc490646889df7286b12d1587e\"",
    "be4aea47-ebdc-4a92-a0c6-3f75780b5e8d": "\"/providers/microsoft.powerapps/apis/shared_logicflows/connections/8c79a64bc046410d9d685541b53c65ec\"",
    "c04a2c06-1d0d-48be-8ce0-aa6df8da7407": "\"/providers/microsoft.powerapps/apis/shared_office365/connections/4e554dfaea13408485f6c19aaeae3a8a\"",
    "da1866a0-09ef-4791-88fb-08115836229e": "\"/providers/microsoft.powerapps/apis/shared_sharepointonline/connections/2a12323711f144ffad14847457f657b8\"",
    "f09932a7-959b-4bd4-8b00-7d221b58bcfa": "\"/providers/microsoft.powerapps/apis/shared_powerbi/connections/72dfdaf2b4644427b5c7e8a69f1c215b\"",
    "fa0d3e20-32f2-4ca2-acd2-3675963a0f06": "\"/providers/microsoft.powerapps/apis/shared_excelonlinebusiness/connections/3d8d9f872eb5407d8de256ce631670b6\""
  },
  "LocalDatabaseReferencesAsEmpty": false,
  "LocalResourceFileNames": {
    "Kelloggs_login": "0001.JPG",
    "Kellogs.KelloggLogo650x366": "0002.png"
  },
  "LocalResourceRootPaths": {
    "Kelloggs_login": "https://docserverpwaprodweu.blob.core.windows.net/c0ad8f33-0a9d-40a6-8d24-c2cca7d9dfa0-1/resource/Assets0Images00001.JPG?sv=2018-03-28&sr=b&sig=iY7Maujz1TwRzgYaIBBiL7CxkI05OO9g%2Fh%2BG3q5uhv0%3D&spr=https&se=2023-04-19T11%3A28%3A48Z&sp=r",
    "Kellogs.KelloggLogo650x366": "https://docserverpwaprodweu.blob.core.windows.net/c0ad8f33-0a9d-40a6-8d24-c2cca7d9dfa0-1/resource/Assets0Images00002.png?sv=2018-03-28&sr=b&sig=uVCRu2zKy1P7413T1girRelH9u8C%2BJ0RA%2BvlFEytEwE%3D&spr=https&se=2023-04-19T11%3A28%3A48Z&sp=r"
  },
  "OrderComponentMetadata": {
    "028175e180d7486f9f0c28262b40d618": 1,
    "edba5150e0cb4e3bb0532a7de693516b": 0
  },
  "OrderComponentTemplate": {
    "028175e180d7486f9f0c28262b40d618": 1,
    "edba5150e0cb4e3bb0532a7de693516b": 0
  },
  "OrderDataSource": {
    "ChoiceCountCollection": 22,
    "ChoiceTextCollection": 23,
    "Claim Attachment": 6,
    "Claim Document Type": 7,
    "Claim Type": 8,
    "colClaimStatus": 24,
    "colClaimType": 25,
    "colDestinationCountry": 26,
    "colHorizontalMenu": 27,
    "ColumnChartSample": 9,
    "ComboBoxSample": 10,
    "customer_claims_1": 11,
    "customer_claims_1_all": 28,
    "CustomGallerySample": 12,
    "DropDownSample": 13,
    "ExportToExcel": 0,
    "FilteredChoiceCountCollection": 29,
    "Generic Status": 14,
    "GetDocumentTypeID": 1,
    "GroupedData": 30,
    "LegendSample": 15,
    "LineChartSample": 16,
    "Market": 17,
    "Office365Outlook": 2,
    "Period": 18,
    "PeriodChoices": 31,
    "PieChartSample": 19,
    "PowerBI": 3,
    "RejectReason_1": 20,
    "SaveAttachmentToSharePoint": 4,
    "statusChoiceDistributor": 32,
    "UniqueCountriesCollection": 33,
    "UploadExcel": 5,
    "users": 21
  },
  "OrderGroupControls": {
    "CompositeColumnChart1": {
      "ColumnChart1": 1,
      "Title1": 0
    },
    "CompositeLineChart1": {
      "LineChart1": 1,
      "Title2": 0
    },
    "CompositePieChart1": {
      "Legend3": 2,
      "PieChart1": 1,
      "Title3": 0
    },
    "Group1_4": {
      "AttachmentControl_4": 2,
      "Button2_4": 0,
      "dd__4": 1,
      "lbl_ClaimType2_4": 3
    },
    "Group3_2": {},
    "Group3_5": {},
    "Group4": {
      "combo_ct_8": 5,
      "combo_status_7": 4,
      "input_search_4": 3,
      "lbl_ClaimType1_12": 1,
      "lbl_SearchKeyword_8": 0,
      "lbl_Status_15": 2
    },
    "Group5": {
      "Label1_84": 0,
      "Label1_85": 1,
      "Label1_86": 2,
      "Label1_87": 3,
      "Label1_88": 4,
      "Label1_89": 5,
      "Label1_90": 6,
      "Label1_91": 7,
      "Label1_92": 8,
      "Label1_93": 9,
      "Label1_94": 10,
      "Label1_95": 11
    },
    "PopupReject": {
      "Button_CancelGoBack_2": 4,
      "Button_reject_2": 3,
      "Icon5": 5,
      "Label1": 2,
      "RectangleOverlay": 0,
      "RectangleRejectReasonPopup": 1,
      "RejectReason": 6,
      "RejectReasonOthers": 7
    }
  },
  "OrderPcfTemplate": {
    "PowerApps_CoreControls_LinkCanvas": 0
  },
  "OrderTemplate": {},
  "OrderXMLTemplate": {
    "attachments": 11,
    "barChart": 15,
    "button": 4,
    "checkbox": 17,
    "combobox": 10,
    "datepicker": 9,
    "dropdown": 12,
    "fluidGrid": 13,
    "form": 8,
    "gallery": 3,
    "groupContainer": 0,
    "icon": 5,
    "image": 2,
    "label": 6,
    "legend": 19,
    "lineChart": 16,
    "pieChart": 18,
    "powerbi": 14,
    "rectangle": 1,
    "text": 7
  },
  "OverridablePropertiesEntry": {
    "Actual ETA_DataCard1": {},
    "Actual ETD_DataCard1": {},
    "ActualETA_TD_6": {},
    "ActualETD_TD_6": {},
    "App": {},
    "Approved Cases_DataCard1": {},
    "AttachmentControl_2": {},
    "AttachmentControl_4": {},
    "BL#_DataCard1": {},
    "BLNo_TD_6": {},
    "BU Comment_DataCard1": {},
    "button_approve": {},
    "Button_CancelGoBack": {},
    "Button_CancelGoBack_2": {},
    "Button_CIN_TD_3": {},
    "Button_delete": {},
    "button_gallery_cin_2": {},
    "button_gallery_cin_4": {},
    "button_gallery_cin_5": {},
    "button_process": {},
    "Button_reject": {},
    "Button_reject_2": {},
    "button_Submit": {},
    "Button2_2": {},
    "Button2_4": {},
    "Button5": {},
    "CancelUpload": {},
    "Canvas2_1": {},
    "cbKPI_ClaimType": {},
    "cbKPI_Market": {},
    "cbKPI_Period": {},
    "CIN (Title)_DataCard1": {},
    "Claim Status_DataCard1": {},
    "Claim Type_DataCard1": {},
    "claim_draft_screen": {},
    "ClaimForm": {},
    "ClaimSubDate_TD_6": {},
    "ClaimType_TD_6": {},
    "ColumnChart1": {},
    "ColumnChart2_2": {},
    "combo_ct_2": {},
    "combo_ct_7": {},
    "combo_ct_8": {},
    "combo_market_3": {},
    "combo_status_2": {},
    "combo_status_6": {},
    "combo_status_7": {},
    "CompositeColumnChart1": {},
    "CompositeLineChart1": {},
    "CompositePieChart1": {},
    "cont_Attachment": {},
    "cont_ClaimDetail": {},
    "cont_PopupGrey": {},
    "Container #_DataCard1": {},
    "Container1": {},
    "Container1_2": {},
    "Container1_5": {},
    "Container1_8": {},
    "Container2": {},
    "Container3": {},
    "Container4": {},
    "Container5": {},
    "Container7_1": {},
    "ContainerErrorETA": {},
    "ContainerErrorKelloggPO": {},
    "ContainerErrorSSCC": {},
    "ContainerNo_TD_6": {},
    "CusReqETA_TD_6": {},
    "Customer Comment_DataCard1": {},
    "Customer PO_DataCard1": {},
    "Customer Requested ETA_DataCard1": {},
    "CustomerPO_TD_6": {},
    "dashboard_btn_10": {},
    "dashboard_btn_11": {},
    "dashboard_btn_3": {},
    "dashboard_btn_5": {},
    "dashboard_btn_7": {},
    "DataCard2_1": {},
    "DataCardKey1": {},
    "DataCardKey10": {},
    "DataCardKey11": {},
    "DataCardKey12": {},
    "DataCardKey13": {},
    "DataCardKey14": {},
    "DataCardKey15": {},
    "DataCardKey16": {},
    "DataCardKey17": {},
    "DataCardKey18": {},
    "DataCardKey19": {},
    "DataCardKey2": {},
    "DataCardKey20": {},
    "DataCardKey21": {},
    "DataCardKey22": {},
    "DataCardKey23": {},
    "DataCardKey24": {},
    "DataCardKey25": {},
    "DataCardKey26": {},
    "DataCardKey27": {},
    "DataCardKey28": {},
    "DataCardKey3": {},
    "DataCardKey4": {},
    "DataCardKey5": {},
    "DataCardKey6": {},
    "DataCardKey7": {},
    "DataCardKey8": {},
    "DataCardKey9": {},
    "DataCardValue1": {},
    "DataCardValue10": {},
    "DataCardValue11": {},
    "DataCardValue12": {},
    "DataCardValue13": {},
    "DataCardValue14": {},
    "DataCardValue15": {},
    "DataCardValue16": {},
    "DataCardValue17": {},
    "DataCardValue18": {},
    "DataCardValue19": {},
    "DataCardValue2": {},
    "DataCardValue20": {},
    "DataCardValue21": {},
    "DataCardValue22": {},
    "DataCardValue23": {},
    "DataCardValue24": {},
    "DataCardValue25": {},
    "DataCardValue26": {},
    "DataCardValue27": {},
    "DataCardValue28": {},
    "DataCardValue3": {},
    "DataCardValue4": {},
    "DataCardValue5": {},
    "DataCardValue6": {},
    "DataCardValue7": {},
    "DataCardValue8": {},
    "DataCardValue9": {},
    "DateBU": {},
    "DateBU_1": {},
    "DateGBS": {},
    "DateGBS_1": {},
    "DateNew": {},
    "DateNew_1": {},
    "DatePIOFinance": {},
    "DatePIOFinance_1": {},
    "DatePIOSPOC": {},
    "DatePIOSPOC_1": {},
    "dd__2": {},
    "dd__4": {},
    "DDRF#_DataCard1": {},
    "DDRF_TD_6": {},
    "draft_btn_11": {},
    "draft_btn_3": {},
    "draft_btn_7": {},
    "draft_btn_9": {},
    "draftclaimdetail_screen": {},
    "ErrorETA": {},
    "ErrorKelloggPO": {},
    "ErrorMessage1": {},
    "ErrorMessage10": {},
    "ErrorMessage11": {},
    "ErrorMessage12": {},
    "ErrorMessage13": {},
    "ErrorMessage14": {},
    "ErrorMessage15": {},
    "ErrorMessage16": {},
    "ErrorMessage17": {},
    "ErrorMessage18": {},
    "ErrorMessage19": {},
    "ErrorMessage2": {},
    "ErrorMessage20": {},
    "ErrorMessage21": {},
    "ErrorMessage22": {},
    "ErrorMessage23": {},
    "ErrorMessage24": {},
    "ErrorMessage25": {},
    "ErrorMessage26": {},
    "ErrorMessage27": {},
    "ErrorMessage28": {},
    "ErrorMessage3": {},
    "ErrorMessage4": {},
    "ErrorMessage5": {},
    "ErrorMessage6": {},
    "ErrorMessage7": {},
    "ErrorMessage8": {},
    "ErrorMessage9": {},
    "ErrorSSCC": {},
    "Estimated Claim Value_DataCard1": {},
    "ExportToExcel_button": {},
    "FileAttachment": {},
    "Final Claim Value_DataCard1": {},
    "FooterContainer1": {},
    "forgot_pswrd": {},
    "Gallery_CreditNote": {},
    "Gallery_DamageImage": {},
    "Gallery_Supporting Documents": {},
    "Gallery_WHReceipt": {},
    "Gallery4_3": {},
    "Gallery4_6": {},
    "GalleryKPI": {},
    "galleryTemplate1": {},
    "galleryTemplate2": {},
    "galleryTemplate3": {},
    "galleryTemplate3_2": {},
    "galleryTemplate3_3": {},
    "galleryTemplate3_6": {},
    "galleryTemplate4_3": {},
    "galleryTemplate4_5": {},
    "galleryTemplate4_6": {},
    "galleryTemplate4_9": {},
    "GBS Comment_DataCard1": {},
    "Group1_4": {},
    "Group3_2": {},
    "Group3_5": {},
    "Group4": {},
    "Group5": {},
    "HeaderClaimDraft_6": {},
    "HeaderContainer1_2": {},
    "HeaderContainer1_5": {},
    "HeaderContainer1_6": {},
    "HeaderContainer1_7": {},
    "HeaderContainer1_9": {},
    "HeaderContainer2": {},
    "HeightSubmenu": {},
    "HorizontalMenuComponent": {},
    "HorizontalMenuComponent_1": {},
    "HorizontalMenuComponent_2": {},
    "Icon_Add_ImageDamage": {},
    "Icon_Add_SupportingDocs": {},
    "Icon_AddCreditNote": {},
    "Icon_AddWHReceipt": {},
    "Icon1_2": {},
    "Icon1_4": {},
    "Icon1_6": {},
    "Icon10": {},
    "Icon11": {},
    "Icon2_5": {},
    "Icon2_7": {},
    "Icon3": {},
    "Icon4_1": {},
    "Icon4_2": {},
    "Icon4_4": {},
    "Icon5": {},
    "Icon5_10": {},
    "Icon5_11": {},
    "Icon5_5": {},
    "Icon5_6": {},
    "Icon5_8": {},
    "Icon6_3": {},
    "Icon6_5": {},
    "Icon6_6": {},
    "Icon6_8": {},
    "Icon6_9": {},
    "Icon7_1": {},
    "Icon7_2": {},
    "Icon8": {},
    "Icon8_1": {},
    "Icon8_2": {},
    "Icon8_6": {},
    "Icon9": {},
    "Icon9_1": {},
    "Icon9_2": {},
    "Icon9_6": {},
    "IconErrorETA": {},
    "IconErrorKelloggPO": {},
    "IconErrorSSCC": {},
    "Image1": {},
    "Image2_10": {},
    "Image2_12": {},
    "Image2_3": {},
    "Image2_5": {},
    "Image2_8": {},
    "Image3_2": {},
    "Image3_4": {},
    "input_search_2": {},
    "input_search_4": {},
    "InvDate_TD_6": {},
    "Invoice Date_DataCard1": {},
    "Kellogg Code_DataCard1": {},
    "Kellogg Inv #_DataCard1": {},
    "Kellogg PO#_DataCard1": {},
    "Kellogg SO#_DataCard1": {},
    "KelloggCode_TD_6": {},
    "KelloggInvNo_TD_6": {},
    "KelloggPO_TD_6": {},
    "KelloggSO_TD_6": {},
    "kpi_btn_1": {},
    "kpi_btn_2": {},
    "kpi_btn_5": {},
    "kpi_screen": {},
    "Label_ActualETA_6": {},
    "Label_ActualETD_6": {},
    "Label_BLNo_6": {},
    "Label_CIN_6": {},
    "Label_ClaimSubDate_6": {},
    "Label_ClaimType_6": {},
    "Label_ContainerNo_6": {},
    "Label_CusReqETA_6": {},
    "Label_CustomerPO_6": {},
    "Label_DDRF_6": {},
    "Label_InvDate_6": {},
    "Label_KelloggCode_6": {},
    "Label_KelloggInvNo_6": {},
    "Label_KelloggPO_6": {},
    "Label_KelloggSO_6": {},
    "Label_ProductDesc_6": {},
    "Label_Quantity_6": {},
    "Label_SSCCNo_6": {},
    "Label_Status_6": {},
    "Label_TotalCases_6": {},
    "Label1": {},
    "Label1_27": {},
    "Label1_28": {},
    "Label1_29": {},
    "Label1_30": {},
    "Label1_31": {},
    "Label1_32": {},
    "Label1_33": {},
    "Label1_34": {},
    "Label1_35": {},
    "Label1_42": {},
    "Label1_43": {},
    "Label1_44": {},
    "Label1_45": {},
    "Label1_46": {},
    "Label1_47": {},
    "Label1_84": {},
    "Label1_85": {},
    "Label1_86": {},
    "Label1_87": {},
    "Label1_88": {},
    "Label1_89": {},
    "Label1_90": {},
    "Label1_91": {},
    "Label1_92": {},
    "Label1_93": {},
    "Label1_94": {},
    "Label1_95": {},
    "Label2": {},
    "Label3_2": {},
    "Label3_5": {},
    "Label4": {},
    "Label5": {},
    "Label5_11": {},
    "Label5_12": {},
    "Label5_13": {},
    "Label5_15": {},
    "Label5_17": {},
    "Label5_20": {},
    "Label5_5": {},
    "Label5_6": {},
    "Label6": {},
    "Label6_1": {},
    "Label6_2": {},
    "Label6_6": {},
    "Label7_4": {},
    "Label7_5": {},
    "Label9_6": {},
    "landing_screen": {},
    "landing_screen_distributor": {},
    "lbl_ClaimType1_11": {},
    "lbl_ClaimType1_12": {},
    "lbl_ClaimType1_6": {},
    "lbl_ClaimType1_8": {},
    "lbl_ClaimType2_2": {},
    "lbl_ClaimType2_4": {},
    "lbl_ecv": {},
    "lbl_faq": {},
    "lbl_fcv": {},
    "lbl_hdn_warnings_2": {},
    "lbl_hdn_warnings_4": {},
    "lbl_hdn_warnings_5": {},
    "lbl_hdn_warnings_7": {},
    "lbl_SearchKeyword_6": {},
    "lbl_SearchKeyword_8": {},
    "lbl_Status_13": {},
    "lbl_Status_14": {},
    "lbl_Status_15": {},
    "lbl_Status_6": {},
    "lbl_Status_8": {},
    "lbl_Status_9": {},
    "lbl_tbl_cd_2": {},
    "lbl_tbl_cd_4": {},
    "lbl_tbl_comments_2": {},
    "lbl_tbl_comments_4": {},
    "lbl_tbl_country_2": {},
    "lbl_tbl_country_4": {},
    "lbl_tbl_country_5": {},
    "lbl_tbl_ct_2": {},
    "lbl_tbl_ct_4": {},
    "lbl_tbl_ct_5": {},
    "lbl_tbl_in_2": {},
    "lbl_tbl_in_4": {},
    "lbl_tbl_in_5": {},
    "lbl_tbl_kpo_2": {},
    "lbl_tbl_kpo_4": {},
    "lbl_tbl_kpo_5": {},
    "lbl_tbl_status_2": {},
    "lbl_tbl_status_4": {},
    "lbl_tbl_tcfc_2": {},
    "lbl_tbl_tcfc_4": {},
    "lbl_tbl_tcfc_5": {},
    "Legend3": {},
    "LineChart1": {},
    "LineChart2_2": {},
    "LinkCanvas1": {},
    "login_btn": {},
    "login_screen": {},
    "Logo": {},
    "MainMenu": {},
    "MainSectionContainer1_2": {},
    "MainSectionContainer1_5": {},
    "MainSectionContainer1_6": {},
    "MainSectionContainer1_7": {},
    "MainSectionContainer1_9": {},
    "MainSectionContainer2": {},
    "menu_screen": {},
    "password_txt": {},
    "PieChart1": {},
    "PIOFinance Comment_DataCard1": {},
    "PIOSPOC Comment_DataCard1": {},
    "PopupReject": {},
    "PowerBI1": {},
    "PowerBI12": {},
    "PowerBI13": {},
    "PowerBI14": {},
    "PowerBI15": {},
    "PowerBI16": {},
    "PowerBI18": {},
    "Product Description _DataCard1": {},
    "ProductDes_TD_6": {},
    "Progress_Trail": {},
    "ProgressBar": {},
    "ProgressBar_1": {},
    "Quantity (cs)_DataCard1": {},
    "Quantity_TD_6": {},
    "Rectangle1": {},
    "Rectangle2": {},
    "Rectangle3": {},
    "Rectangle4": {},
    "Rectangle5": {},
    "Rectangle6": {},
    "Rectangle6_10": {},
    "Rectangle6_11": {},
    "Rectangle6_2": {},
    "Rectangle6_3": {},
    "Rectangle6_4": {},
    "Rectangle6_5": {},
    "Rectangle6_6": {},
    "Rectangle6_7": {},
    "Rectangle6_8": {},
    "Rectangle6_9": {},
    "Rectangle7_10": {},
    "Rectangle7_11": {},
    "Rectangle7_3": {},
    "Rectangle7_5": {},
    "Rectangle7_7": {},
    "RectangleOverlay": {},
    "RectangleRejectReasonPopup": {},
    "RejectReason": {},
    "RejectReasonOthers": {},
    "remember_cb": {},
    "SaveDocument": {},
    "ScreenContainer1_10": {},
    "ScreenContainer1_2": {},
    "ScreenContainer1_5": {},
    "ScreenContainer1_6": {},
    "ScreenContainer1_7": {},
    "ScreenContainer2": {},
    "SearchInput_6": {},
    "SSCC#_DataCard1": {},
    "SSCC_TD_6": {},
    "StarVisible1": {},
    "StarVisible10": {},
    "StarVisible11": {},
    "StarVisible12": {},
    "StarVisible13": {},
    "StarVisible14": {},
    "StarVisible15": {},
    "StarVisible16": {},
    "StarVisible17": {},
    "StarVisible18": {},
    "StarVisible19": {},
    "StarVisible2": {},
    "StarVisible20": {},
    "StarVisible21": {},
    "StarVisible22": {},
    "StarVisible23": {},
    "StarVisible24": {},
    "StarVisible25": {},
    "StarVisible26": {},
    "StarVisible27": {},
    "StarVisible28": {},
    "StarVisible3": {},
    "StarVisible4": {},
    "StarVisible5": {},
    "StarVisible6": {},
    "StarVisible7": {},
    "StarVisible8": {},
    "StarVisible9": {},
    "status_screen": {},
    "Status_TD_6": {},
    "StatusIcon_10": {},
    "StatusIcon_11": {},
    "StatusIcon_2": {},
    "StatusIcon_3": {},
    "StatusIcon_4": {},
    "StatusIcon_5": {},
    "StatusIcon_6": {},
    "StatusIcon_7": {},
    "StatusIcon_8": {},
    "StatusIcon_9": {},
    "Submenu": {},
    "Submission Date_DataCard1": {},
    "TableClaimDraft_6": {},
    "TableDataClaimDraft_6": {},
    "Title1": {},
    "Title2": {},
    "Title3": {},
    "Title4_10": {},
    "Title4_11": {},
    "Title4_2": {},
    "Title4_3": {},
    "Title4_4": {},
    "Title4_5": {},
    "Title4_6": {},
    "Title4_7": {},
    "Title4_8": {},
    "Title4_9": {},
    "Total cases for Claim_DataCard1": {},
    "TotalCases_TD_6": {},
    "username": {},
    "username_txt": {}
  },
  "PCFDynamicSchemaForIRRetrievalEntry": {},
  "PCFTemplateEntry": {
    "LinkCanvas1": {
      "CustomGroupControlTemplateName": "",
      "DynamicControlDefinitionJson": "{\"ControlNamespace\":\"PowerApps.CoreControls\",\"ControlConstructor\":\"LinkCanvas\",\"DisplayNameKey\":\"LinkCanvas\",\"Resources\":\"[{\\\"Type\\\":0,\\\"Path\\\":\\\"/PCF/prop-types.js\\\",\\\"ModifiedPath\\\":\\\"\\\",\\\"LoadingOrder\\\":1,\\\"IsControlSpecific\\\":false},{\\\"Type\\\":0,\\\"Path\\\":\\\"/PCF/react-fela.js\\\",\\\"ModifiedPath\\\":\\\"\\\",\\\"LoadingOrder\\\":2,\\\"IsControlSpecific\\\":false},{\\\"Type\\\":0,\\\"Path\\\":\\\"/PCF/fela.js\\\",\\\"ModifiedPath\\\":\\\"\\\",\\\"LoadingOrder\\\":3,\\\"IsControlSpecific\\\":false},{\\\"Type\\\":0,\\\"Path\\\":\\\"/PCF/fela-dom.js\\\",\\\"ModifiedPath\\\":\\\"\\\",\\\"LoadingOrder\\\":4,\\\"IsControlSpecific\\\":false},{\\\"Type\\\":0,\\\"Path\\\":\\\"/ctrllib/PCFControls/js/PCFControlWrapper.js\\\",\\\"ModifiedPath\\\":\\\"\\\",\\\"LoadingOrder\\\":6,\\\"IsControlSpecific\\\":false},{\\\"Type\\\":0,\\\"Path\\\":\\\"/ctrllib/PcfControlProxy/js/PcfControlProxy.js\\\",\\\"ModifiedPath\\\":\\\"\\\",\\\"LoadingOrder\\\":7,\\\"IsControlSpecific\\\":false},{\\\"Type\\\":3,\\\"Path\\\":\\\"{\\\\\\\"Id\\\\\\\":\\\\\\\"ManifestTemplate\\\\\\\",\\\\\\\"Data\\\\\\\":{\\\\\\\"ConstructorName\\\\\\\":\\\\\\\"PowerApps.CoreControls.LinkCanvas\\\\\\\",\\\\\\\"CustomControlId\\\\\\\":\\\\\\\"PowerApps.CoreControls.LinkCanvas\\\\\\\",\\\\\\\"IsVirtual\\\\\\\":true,\\\\\\\"Properties\\\\\\\":{\\\\\\\"Resources\\\\\\\":[{\\\\\\\"Name\\\\\\\":\\\\\\\"/PCF/prop-types.js\\\\\\\",\\\\\\\"LoadOrder\\\\\\\":1,\\\\\\\"Type\\\\\\\":0,\\\\\\\"LibraryName\\\\\\\":null},{\\\\\\\"Name\\\\\\\":\\\\\\\"/PCF/react-fela.js\\\\\\\",\\\\\\\"LoadOrder\\\\\\\":2,\\\\\\\"Type\\\\\\\":0,\\\\\\\"LibraryName\\\\\\\":null},{\\\\\\\"Name\\\\\\\":\\\\\\\"/PCF/fela.js\\\\\\\",\\\\\\\"LoadOrder\\\\\\\":3,\\\\\\\"Type\\\\\\\":0,\\\\\\\"LibraryName\\\\\\\":null},{\\\\\\\"Name\\\\\\\":\\\\\\\"/PCF/fela-dom.js\\\\\\\",\\\\\\\"LoadOrder\\\\\\\":4,\\\\\\\"Type\\\\\\\":0,\\\\\\\"LibraryName\\\\\\\":null},{\\\\\\\"Name\\\\\\\":\\\\\\\"/ctrllib/PCFControls/js/PCFControlWrapper.js\\\\\\\",\\\\\\\"LoadOrder\\\\\\\":6,\\\\\\\"Type\\\\\\\":0,\\\\\\\"LibraryName\\\\\\\":null},{\\\\\\\"Name\\\\\\\":\\\\\\\"/ctrllib/PcfControlProxy/js/PcfControlProxy.js\\\\\\\",\\\\\\\"LoadOrder\\\\\\\":7,\\\\\\\"Type\\\\\\\":0,\\\\\\\"LibraryName\\\\\\\":null}],\\\\\\\"GroupDefinitions\\\\\\\":null,\\\\\\\"DataSetDefinitions\\\\\\\":{},\\\\\\\"Properties\\\\\\\":{\\\\\\\"AcceptsFocus\\\\\\\":{\\\\\\\"Required\\\\\\\":true,\\\\\\\"Usage\\\\\\\":1,\\\\\\\"DefaultValue\\\\\\\":\\\\\\\"true\\\\\\\"},\\\\\\\"AccessibleLabel\\\\\\\":{\\\\\\\"Required\\\\\\\":true,\\\\\\\"Usage\\\\\\\":1,\\\\\\\"DefaultValue\\\\\\\":\\\\\\\"Link\\\\\\\"},\\\\\\\"Text\\\\\\\":{\\\\\\\"Required\\\\\\\":true,\\\\\\\"Usage\\\\\\\":1,\\\\\\\"DefaultValue\\\\\\\":\\\\\\\"Link\\\\\\\"},\\\\\\\"URL\\\\\\\":{\\\\\\\"Required\\\\\\\":true,\\\\\\\"Usage\\\\\\\":1,\\\\\\\"DefaultValue\\\\\\\":\\\\\\\"\\\\\\\"},\\\\\\\"TabIndex\\\\\\\":{\\\\\\\"Required\\\\\\\":true,\\\\\\\"Usage\\\\\\\":1,\\\\\\\"DefaultValue\\\\\\\":\\\\\\\"\\\\\\\"},\\\\\\\"Tooltip\\\\\\\":{\\\\\\\"Required\\\\\\\":true,\\\\\\\"Usage\\\\\\\":1,\\\\\\\"DefaultValue\\\\\\\":\\\\\\\"\\\\\\\"}},\\\\\\\"FeatureUsage\\\\\\\":null},\\\\\\\"Events\\\\\\\":null,\\\\\\\"CommonEvents\\\\\\\":null,\\\\\\\"DesignMap\\\\\\\":null,\\\\\\\"PropertyDependencies\\\\\\\":[],\\\\\\\"Children\\\\\\\":null}}\\\",\\\"ModifiedPath\\\":\\\"\\\",\\\"LoadingOrder\\\":7,\\\"IsControlSpecific\\\":false},{\\\"Type\\\":3,\\\"Path\\\":\\\"{\\\\\\\"Id\\\\\\\":\\\\\\\"ManifestPropertyTypes\\\\\\\",\\\\\\\"Data\\\\\\\":{\\\\\\\"Properties\\\\\\\":[{\\\\\\\"Name\\\\\\\":\\\\\\\"AcceptsFocus\\\\\\\",\\\\\\\"Type\\\\\\\":\\\\\\\"TwoOptions\\\\\\\",\\\\\\\"ComplexType\\\\\\\":\\\\\\\"\\\\\\\",\\\\\\\"IsPrimary\\\\\\\":false,\\\\\\\"IsIncluded\\\\\\\":false},{\\\\\\\"Name\\\\\\\":\\\\\\\"AccessibleLabel\\\\\\\",\\\\\\\"Type\\\\\\\":\\\\\\\"SingleLine_Text\\\\\\\",\\\\\\\"ComplexType\\\\\\\":\\\\\\\"None\\\\\\\",\\\\\\\"IsPrimary\\\\\\\":false,\\\\\\\"IsIncluded\\\\\\\":false},{\\\\\\\"Name\\\\\\\":\\\\\\\"Text\\\\\\\",\\\\\\\"Type\\\\\\\":\\\\\\\"SingleLine_Text\\\\\\\",\\\\\\\"ComplexType\\\\\\\":\\\\\\\"None\\\\\\\",\\\\\\\"IsPrimary\\\\\\\":false,\\\\\\\"IsIncluded\\\\\\\":false},{\\\\\\\"Name\\\\\\\":\\\\\\\"URL\\\\\\\",\\\\\\\"Type\\\\\\\":\\\\\\\"SingleLine_Text\\\\\\\",\\\\\\\"ComplexType\\\\\\\":\\\\\\\"None\\\\\\\",\\\\\\\"IsPrimary\\\\\\\":true,\\\\\\\"IsIncluded\\\\\\\":false},{\\\\\\\"Name\\\\\\\":\\\\\\\"TabIndex\\\\\\\",\\\\\\\"Type\\\\\\\":\\\\\\\"Whole_None\\\\\\\",\\\\\\\"ComplexType\\\\\\\":\\\\\\\"\\\\\\\",\\\\\\\"IsPrimary\\\\\\\":false,\\\\\\\"IsIncluded\\\\\\\":false},{\\\\\\\"Name\\\\\\\":\\\\\\\"Tooltip\\\\\\\",\\\\\\\"Type\\\\\\\":\\\\\\\"SingleLine_Text\\\\\\\",\\\\\\\"ComplexType\\\\\\\":\\\\\\\"\\\\\\\",\\\\\\\"IsPrimary\\\\\\\":false,\\\\\\\"IsIncluded\\\\\\\":false},{\\\\\\\"Name\\\\\\\":\\\\\\\"PCFTeamsTheme\\\\\\\",\\\\\\\"Type\\\\\\\":\\\\\\\"String\\\\\\\",\\\\\\\"ComplexType\\\\\\\":\\\\\\\"\\\\\\\",\\\\\\\"IsPrimary\\\\\\\":false,\\\\\\\"IsIncluded\\\\\\\":true},{\\\\\\\"Name\\\\\\\":\\\\\\\"X\\\\\\\",\\\\\\\"Type\\\\\\\":\\\\\\\"Number\\\\\\\",\\\\\\\"ComplexType\\\\\\\":\\\\\\\"\\\\\\\",\\\\\\\"IsPrimary\\\\\\\":false,\\\\\\\"IsIncluded\\\\\\\":true},{\\\\\\\"Name\\\\\\\":\\\\\\\"Y\\\\\\\",\\\\\\\"Type\\\\\\\":\\\\\\\"Number\\\\\\\",\\\\\\\"ComplexType\\\\\\\":\\\\\\\"\\\\\\\",\\\\\\\"IsPrimary\\\\\\\":false,\\\\\\\"IsIncluded\\\\\\\":true},{\\\\\\\"Name\\\\\\\":\\\\\\\"Width\\\\\\\",\\\\\\\"Type\\\\\\\":\\\\\\\"Number\\\\\\\",\\\\\\\"ComplexType\\\\\\\":\\\\\\\"\\\\\\\",\\\\\\\"IsPrimary\\\\\\\":false,\\\\\\\"IsIncluded\\\\\\\":true},{\\\\\\\"Name\\\\\\\":\\\\\\\"Height\\\\\\\",\\\\\\\"Type\\\\\\\":\\\\\\\"Number\\\\\\\",\\\\\\\"ComplexType\\\\\\\":\\\\\\\"\\\\\\\",\\\\\\\"IsPrimary\\\\\\\":false,\\\\\\\"IsIncluded\\\\\\\":true},{\\\\\\\"Name\\\\\\\":\\\\\\\"Visible\\\\\\\",\\\\\\\"Type\\\\\\\":\\\\\\\"Boolean\\\\\\\",\\\\\\\"ComplexType\\\\\\\":\\\\\\\"\\\\\\\",\\\\\\\"IsPrimary\\\\\\\":false,\\\\\\\"IsIncluded\\\\\\\":true},{\\\\\\\"Name\\\\\\\":\\\\\\\"DisplayMode\\\\\\\",\\\\\\\"Type\\\\\\\":\\\\\\\"DisplayMode\\\\\\\",\\\\\\\"ComplexType\\\\\\\":\\\\\\\"\\\\\\\",\\\\\\\"IsPrimary\\\\\\\":false,\\\\\\\"IsIncluded\\\\\\\":true}]}}\\\",\\\"ModifiedPath\\\":\\\"\\\",\\\"LoadingOrder\\\":8,\\\"IsControlSpecific\\\":false},{\\\"Type\\\":3,\\\"Path\\\":\\\"{\\\\\\\"Id\\\\\\\":\\\\\\\"PowerAppsControlInfo\\\\\\\",\\\\\\\"Data\\\\\\\":{\\\\\\\"TemplateVersion\\\\\\\":1,\\\\\\\"Version\\\\\\\":\\\\\\\"0.0.12\\\\\\\",\\\\\\\"IsFirstParty\\\\\\\":true}}\\\",\\\"ModifiedPath\\\":\\\"\\\",\\\"LoadingOrder\\\":9,\\\"IsControlSpecific\\\":false},{\\\"Type\\\":0,\\\"Path\\\":\\\"/PCFControls/PowerApps_CoreControls_LinkCanvas/LinkCanvas.js\\\",\\\"ModifiedPath\\\":\\\"\\\",\\\"LoadingOrder\\\":10,\\\"IsControlSpecific\\\":true},{\\\"Type\\\":2,\\\"Path\\\":\\\"/PCFControls/PowerApps_CoreControls_LinkCanvas/strings/LinkCanvas.1033.resx\\\",\\\"ModifiedPath\\\":\\\"\\\",\\\"LoadingOrder\\\":9,\\\"IsControlSpecific\\\":true},{\\\"Type\\\":3,\\\"Path\\\":\\\"{\\\\\\\"Id\\\\\\\":\\\\\\\"FormattingData\\\\\\\",\\\\\\\"Data\\\\\\\":{\\\\\\\"timeZoneUtcOffsetMinutes\\\\\\\":0,\\\\\\\"dateTimeFormatInfo\\\\\\\":{\\\\\\\"AMDesignator\\\\\\\":\\\\\\\"AM\\\\\\\",\\\\\\\"Calendar\\\\\\\":{\\\\\\\"MinSupportedDateTime\\\\\\\":\\\\\\\"0001-01-01T00:00:00\\\\\\\",\\\\\\\"MaxSupportedDateTime\\\\\\\":\\\\\\\"9999-12-31T23:59:59.9999999\\\\\\\",\\\\\\\"AlgorithmType\\\\\\\":1,\\\\\\\"CalendarType\\\\\\\":1,\\\\\\\"Eras\\\\\\\":[1],\\\\\\\"TwoDigitYearMax\\\\\\\":2029,\\\\\\\"IsReadOnly\\\\\\\":false},\\\\\\\"DateSeparator\\\\\\\":\\\\\\\"/\\\\\\\",\\\\\\\"FirstDayOfWeek\\\\\\\":1,\\\\\\\"CalendarWeekRule\\\\\\\":2,\\\\\\\"FullDateTimePattern\\\\\\\":\\\\\\\"dd MMMM yyyy HH:mm:ss\\\\\\\",\\\\\\\"LongDatePattern\\\\\\\":\\\\\\\"dd MMMM yyyy\\\\\\\",\\\\\\\"LongTimePattern\\\\\\\":\\\\\\\"HH:mm:ss\\\\\\\",\\\\\\\"MonthDayPattern\\\\\\\":\\\\\\\"d MMMM\\\\\\\",\\\\\\\"PMDesignator\\\\\\\":\\\\\\\"PM\\\\\\\",\\\\\\\"RFC1123Pattern\\\\\\\":\\\\\\\"ddd, dd MMM yyyy HH':'mm':'ss 'GMT'\\\\\\\",\\\\\\\"ShortDatePattern\\\\\\\":\\\\\\\"dd/MM/yyyy\\\\\\\",\\\\\\\"ShortTimePattern\\\\\\\":\\\\\\\"HH:mm\\\\\\\",\\\\\\\"SortableDateTimePattern\\\\\\\":\\\\\\\"yyyy'-'MM'-'dd'T'HH':'mm':'ss\\\\\\\",\\\\\\\"TimeSeparator\\\\\\\":\\\\\\\":\\\\\\\",\\\\\\\"UniversalSortableDateTimePattern\\\\\\\":\\\\\\\"yyyy'-'MM'-'dd HH':'mm':'ss'Z'\\\\\\\",\\\\\\\"YearMonthPattern\\\\\\\":\\\\\\\"MMMM yyyy\\\\\\\",\\\\\\\"AbbreviatedDayNames\\\\\\\":[\\\\\\\"Sun\\\\\\\",\\\\\\\"Mon\\\\\\\",\\\\\\\"Tue\\\\\\\",\\\\\\\"Wed\\\\\\\",\\\\\\\"Thu\\\\\\\",\\\\\\\"Fri\\\\\\\",\\\\\\\"Sat\\\\\\\"],\\\\\\\"ShortestDayNames\\\\\\\":[\\\\\\\"Su\\\\\\\",\\\\\\\"Mo\\\\\\\",\\\\\\\"Tu\\\\\\\",\\\\\\\"We\\\\\\\",\\\\\\\"Th\\\\\\\",\\\\\\\"Fr\\\\\\\",\\\\\\\"Sa\\\\\\\"],\\\\\\\"DayNames\\\\\\\":[\\\\\\\"Sunday\\\\\\\",\\\\\\\"Monday\\\\\\\",\\\\\\\"Tuesday\\\\\\\",\\\\\\\"Wednesday\\\\\\\",\\\\\\\"Thursday\\\\\\\",\\\\\\\"Friday\\\\\\\",\\\\\\\"Saturday\\\\\\\"],\\\\\\\"AbbreviatedMonthNames\\\\\\\":[\\\\\\\"Jan\\\\\\\",\\\\\\\"Feb\\\\\\\",\\\\\\\"Mar\\\\\\\",\\\\\\\"Apr\\\\\\\",\\\\\\\"May\\\\\\\",\\\\\\\"Jun\\\\\\\",\\\\\\\"Jul\\\\\\\",\\\\\\\"Aug\\\\\\\",\\\\\\\"Sep\\\\\\\",\\\\\\\"Oct\\\\\\\",\\\\\\\"Nov\\\\\\\",\\\\\\\"Dec\\\\\\\",\\\\\\\"\\\\\\\"],\\\\\\\"MonthNames\\\\\\\":[\\\\\\\"January\\\\\\\",\\\\\\\"February\\\\\\\",\\\\\\\"March\\\\\\\",\\\\\\\"April\\\\\\\",\\\\\\\"May\\\\\\\",\\\\\\\"June\\\\\\\",\\\\\\\"July\\\\\\\",\\\\\\\"August\\\\\\\",\\\\\\\"September\\\\\\\",\\\\\\\"October\\\\\\\",\\\\\\\"November\\\\\\\",\\\\\\\"December\\\\\\\",\\\\\\\"\\\\\\\"],\\\\\\\"IsReadOnly\\\\\\\":false,\\\\\\\"NativeCalendarName\\\\\\\":\\\\\\\"Gregorian Calendar\\\\\\\",\\\\\\\"AbbreviatedMonthGenitiveNames\\\\\\\":[\\\\\\\"Jan\\\\\\\",\\\\\\\"Feb\\\\\\\",\\\\\\\"Mar\\\\\\\",\\\\\\\"Apr\\\\\\\",\\\\\\\"May\\\\\\\",\\\\\\\"Jun\\\\\\\",\\\\\\\"Jul\\\\\\\",\\\\\\\"Aug\\\\\\\",\\\\\\\"Sep\\\\\\\",\\\\\\\"Oct\\\\\\\",\\\\\\\"Nov\\\\\\\",\\\\\\\"Dec\\\\\\\",\\\\\\\"\\\\\\\"],\\\\\\\"MonthGenitiveNames\\\\\\\":[\\\\\\\"January\\\\\\\",\\\\\\\"February\\\\\\\",\\\\\\\"March\\\\\\\",\\\\\\\"April\\\\\\\",\\\\\\\"May\\\\\\\",\\\\\\\"June\\\\\\\",\\\\\\\"July\\\\\\\",\\\\\\\"August\\\\\\\",\\\\\\\"September\\\\\\\",\\\\\\\"October\\\\\\\",\\\\\\\"November\\\\\\\",\\\\\\\"December\\\\\\\",\\\\\\\"\\\\\\\"]},\\\\\\\"numberFormatInfo\\\\\\\":{\\\\\\\"CurrencyDecimalDigits\\\\\\\":2,\\\\\\\"CurrencyDecimalSeparator\\\\\\\":\\\\\\\".\\\\\\\",\\\\\\\"IsReadOnly\\\\\\\":false,\\\\\\\"CurrencyGroupSizes\\\\\\\":[3],\\\\\\\"NumberGroupSizes\\\\\\\":[3],\\\\\\\"PercentGroupSizes\\\\\\\":[3],\\\\\\\"CurrencyGroupSeparator\\\\\\\":\\\\\\\",\\\\\\\",\\\\\\\"CurrencySymbol\\\\\\\":\\\\\\\"£\\\\\\\",\\\\\\\"NaNSymbol\\\\\\\":\\\\\\\"NaN\\\\\\\",\\\\\\\"CurrencyNegativePattern\\\\\\\":1,\\\\\\\"NumberNegativePattern\\\\\\\":1,\\\\\\\"PercentPositivePattern\\\\\\\":1,\\\\\\\"PercentNegativePattern\\\\\\\":1,\\\\\\\"NegativeInfinitySymbol\\\\\\\":\\\\\\\"-∞\\\\\\\",\\\\\\\"NegativeSign\\\\\\\":\\\\\\\"-\\\\\\\",\\\\\\\"NumberDecimalDigits\\\\\\\":2,\\\\\\\"NumberDecimalSeparator\\\\\\\":\\\\\\\".\\\\\\\",\\\\\\\"NumberGroupSeparator\\\\\\\":\\\\\\\",\\\\\\\",\\\\\\\"CurrencyPositivePattern\\\\\\\":0,\\\\\\\"PositiveInfinitySymbol\\\\\\\":\\\\\\\"∞\\\\\\\",\\\\\\\"PositiveSign\\\\\\\":\\\\\\\"+\\\\\\\",\\\\\\\"PercentDecimalDigits\\\\\\\":2,\\\\\\\"PercentDecimalSeparator\\\\\\\":\\\\\\\".\\\\\\\",\\\\\\\"PercentGroupSeparator\\\\\\\":\\\\\\\",\\\\\\\",\\\\\\\"PercentSymbol\\\\\\\":\\\\\\\"%\\\\\\\",\\\\\\\"PerMilleSymbol\\\\\\\":\\\\\\\"‰\\\\\\\",\\\\\\\"NativeDigits\\\\\\\":[\\\\\\\"0\\\\\\\",\\\\\\\"1\\\\\\\",\\\\\\\"2\\\\\\\",\\\\\\\"3\\\\\\\",\\\\\\\"4\\\\\\\",\\\\\\\"5\\\\\\\",\\\\\\\"6\\\\\\\",\\\\\\\"7\\\\\\\",\\\\\\\"8\\\\\\\",\\\\\\\"9\\\\\\\"],\\\\\\\"DigitSubstitution\\\\\\\":1},\\\\\\\"timeZoneAdjusters\\\\\\\":[],\\\\\\\"formatInfoCultureName\\\\\\\":\\\\\\\"en-GB\\\\\\\",\\\\\\\"formatter\\\\\\\":null,\\\\\\\"languagesByCode\\\\\\\":{\\\\\\\"2057\\\\\\\":\\\\\\\"English (United Kingdom)\\\\\\\",\\\\\\\"-1\\\\\\\":\\\\\\\"All Languages\\\\\\\"}}}\\\",\\\"ModifiedPath\\\":\\\"\\\",\\\"LoadingOrder\\\":12,\\\"IsControlSpecific\\\":false},{\\\"Type\\\":5,\\\"Path\\\":\\\"/PCFControls/PowerApps_CoreControls_LinkCanvas/strings/LinkCanvas.1025.json\\\",\\\"ModifiedPath\\\":\\\"\\\",\\\"LoadingOrder\\\":13,\\\"IsControlSpecific\\\":true},{\\\"Type\\\":5,\\\"Path\\\":\\\"/PCFControls/PowerApps_CoreControls_LinkCanvas/strings/LinkCanvas.1026.json\\\",\\\"ModifiedPath\\\":\\\"\\\",\\\"LoadingOrder\\\":13,\\\"IsControlSpecific\\\":true},{\\\"Type\\\":5,\\\"Path\\\":\\\"/PCFControls/PowerApps_CoreControls_LinkCanvas/strings/LinkCanvas.1027.json\\\",\\\"ModifiedPath\\\":\\\"\\\",\\\"LoadingOrder\\\":13,\\\"IsControlSpecific\\\":true},{\\\"Type\\\":5,\\\"Path\\\":\\\"/PCFControls/PowerApps_CoreControls_LinkCanvas/strings/LinkCanvas.1028.json\\\",\\\"ModifiedPath\\\":\\\"\\\",\\\"LoadingOrder\\\":13,\\\"IsControlSpecific\\\":true},{\\\"Type\\\":5,\\\"Path\\\":\\\"/PCFControls/PowerApps_CoreControls_LinkCanvas/strings/LinkCanvas.1029.json\\\",\\\"ModifiedPath\\\":\\\"\\\",\\\"LoadingOrder\\\":13,\\\"IsControlSpecific\\\":true},{\\\"Type\\\":5,\\\"Path\\\":\\\"/PCFControls/PowerApps_CoreControls_LinkCanvas/strings/LinkCanvas.1030.json\\\",\\\"ModifiedPath\\\":\\\"\\\",\\\"LoadingOrder\\\":13,\\\"IsControlSpecific\\\":true},{\\\"Type\\\":5,\\\"Path\\\":\\\"/PCFControls/PowerApps_CoreControls_LinkCanvas/strings/LinkCanvas.1031.json\\\",\\\"ModifiedPath\\\":\\\"\\\",\\\"LoadingOrder\\\":13,\\\"IsControlSpecific\\\":true},{\\\"Type\\\":5,\\\"Path\\\":\\\"/PCFControls/PowerApps_CoreControls_LinkCanvas/strings/LinkCanvas.1032.json\\\",\\\"ModifiedPath\\\":\\\"\\\",\\\"LoadingOrder\\\":13,\\\"IsControlSpecific\\\":true},{\\\"Type\\\":5,\\\"Path\\\":\\\"/PCFControls/PowerApps_CoreControls_LinkCanvas/strings/LinkCanvas.1033.json\\\",\\\"ModifiedPath\\\":\\\"\\\",\\\"LoadingOrder\\\":13,\\\"IsControlSpecific\\\":true},{\\\"Type\\\":5,\\\"Path\\\":\\\"/PCFControls/PowerApps_CoreControls_LinkCanvas/strings/LinkCanvas.1035.json\\\",\\\"ModifiedPath\\\":\\\"\\\",\\\"LoadingOrder\\\":13,\\\"IsControlSpecific\\\":true},{\\\"Type\\\":5,\\\"Path\\\":\\\"/PCFControls/PowerApps_CoreControls_LinkCanvas/strings/LinkCanvas.1036.json\\\",\\\"ModifiedPath\\\":\\\"\\\",\\\"LoadingOrder\\\":13,\\\"IsControlSpecific\\\":true},{\\\"Type\\\":5,\\\"Path\\\":\\\"/PCFControls/PowerApps_CoreControls_LinkCanvas/strings/LinkCanvas.1037.json\\\",\\\"ModifiedPath\\\":\\\"\\\",\\\"LoadingOrder\\\":13,\\\"IsControlSpecific\\\":true},{\\\"Type\\\":5,\\\"Path\\\":\\\"/PCFControls/PowerApps_CoreControls_LinkCanvas/strings/LinkCanvas.1038.json\\\",\\\"ModifiedPath\\\":\\\"\\\",\\\"LoadingOrder\\\":13,\\\"IsControlSpecific\\\":true},{\\\"Type\\\":5,\\\"Path\\\":\\\"/PCFControls/PowerApps_CoreControls_LinkCanvas/strings/LinkCanvas.1040.json\\\",\\\"ModifiedPath\\\":\\\"\\\",\\\"LoadingOrder\\\":13,\\\"IsControlSpecific\\\":true},{\\\"Type\\\":5,\\\"Path\\\":\\\"/PCFControls/PowerApps_CoreControls_LinkCanvas/strings/LinkCanvas.1041.json\\\",\\\"ModifiedPath\\\":\\\"\\\",\\\"LoadingOrder\\\":13,\\\"IsControlSpecific\\\":true},{\\\"Type\\\":5,\\\"Path\\\":\\\"/PCFControls/PowerApps_CoreControls_LinkCanvas/strings/LinkCanvas.1042.json\\\",\\\"ModifiedPath\\\":\\\"\\\",\\\"LoadingOrder\\\":13,\\\"IsControlSpecific\\\":true},{\\\"Type\\\":5,\\\"Path\\\":\\\"/PCFControls/PowerApps_CoreControls_LinkCanvas/strings/LinkCanvas.1043.json\\\",\\\"ModifiedPath\\\":\\\"\\\",\\\"LoadingOrder\\\":13,\\\"IsControlSpecific\\\":true},{\\\"Type\\\":5,\\\"Path\\\":\\\"/PCFControls/PowerApps_CoreControls_LinkCanvas/strings/LinkCanvas.1044.json\\\",\\\"ModifiedPath\\\":\\\"\\\",\\\"LoadingOrder\\\":13,\\\"IsControlSpecific\\\":true},{\\\"Type\\\":5,\\\"Path\\\":\\\"/PCFControls/PowerApps_CoreControls_LinkCanvas/strings/LinkCanvas.1045.json\\\",\\\"ModifiedPath\\\":\\\"\\\",\\\"LoadingOrder\\\":13,\\\"IsControlSpecific\\\":true},{\\\"Type\\\":5,\\\"Path\\\":\\\"/PCFControls/PowerApps_CoreControls_LinkCanvas/strings/LinkCanvas.1046.json\\\",\\\"ModifiedPath\\\":\\\"\\\",\\\"LoadingOrder\\\":13,\\\"IsControlSpecific\\\":true},{\\\"Type\\\":5,\\\"Path\\\":\\\"/PCFControls/PowerApps_CoreControls_LinkCanvas/strings/LinkCanvas.1048.json\\\",\\\"ModifiedPath\\\":\\\"\\\",\\\"LoadingOrder\\\":13,\\\"IsControlSpecific\\\":true},{\\\"Type\\\":5,\\\"Path\\\":\\\"/PCFControls/PowerApps_CoreControls_LinkCanvas/strings/LinkCanvas.1049.json\\\",\\\"ModifiedPath\\\":\\\"\\\",\\\"LoadingOrder\\\":13,\\\"IsControlSpecific\\\":true},{\\\"Type\\\":5,\\\"Path\\\":\\\"/PCFControls/PowerApps_CoreControls_LinkCanvas/strings/LinkCanvas.1050.json\\\",\\\"ModifiedPath\\\":\\\"\\\",\\\"LoadingOrder\\\":13,\\\"IsControlSpecific\\\":true},{\\\"Type\\\":5,\\\"Path\\\":\\\"/PCFControls/PowerApps_CoreControls_LinkCanvas/strings/LinkCanvas.1051.json\\\",\\\"ModifiedPath\\\":\\\"\\\",\\\"LoadingOrder\\\":13,\\\"IsControlSpecific\\\":true},{\\\"Type\\\":5,\\\"Path\\\":\\\"/PCFControls/PowerApps_CoreControls_LinkCanvas/strings/LinkCanvas.1053.json\\\",\\\"ModifiedPath\\\":\\\"\\\",\\\"LoadingOrder\\\":13,\\\"IsControlSpecific\\\":true},{\\\"Type\\\":5,\\\"Path\\\":\\\"/PCFControls/PowerApps_CoreControls_LinkCanvas/strings/LinkCanvas.1054.json\\\",\\\"ModifiedPath\\\":\\\"\\\",\\\"LoadingOrder\\\":13,\\\"IsControlSpecific\\\":true},{\\\"Type\\\":5,\\\"Path\\\":\\\"/PCFControls/PowerApps_CoreControls_LinkCanvas/strings/LinkCanvas.1055.json\\\",\\\"ModifiedPath\\\":\\\"\\\",\\\"LoadingOrder\\\":13,\\\"IsControlSpecific\\\":true},{\\\"Type\\\":5,\\\"Path\\\":\\\"/PCFControls/PowerApps_CoreControls_LinkCanvas/strings/LinkCanvas.1057.json\\\",\\\"ModifiedPath\\\":\\\"\\\",\\\"LoadingOrder\\\":13,\\\"IsControlSpecific\\\":true},{\\\"Type\\\":5,\\\"Path\\\":\\\"/PCFControls/PowerApps_CoreControls_LinkCanvas/strings/LinkCanvas.1058.json\\\",\\\"ModifiedPath\\\":\\\"\\\",\\\"LoadingOrder\\\":13,\\\"IsControlSpecific\\\":true},{\\\"Type\\\":5,\\\"Path\\\":\\\"/PCFControls/PowerApps_CoreControls_LinkCanvas/strings/LinkCanvas.1060.json\\\",\\\"ModifiedPath\\\":\\\"\\\",\\\"LoadingOrder\\\":13,\\\"IsControlSpecific\\\":true},{\\\"Type\\\":5,\\\"Path\\\":\\\"/PCFControls/PowerApps_CoreControls_LinkCanvas/strings/LinkCanvas.1061.json\\\",\\\"ModifiedPath\\\":\\\"\\\",\\\"LoadingOrder\\\":13,\\\"IsControlSpecific\\\":true},{\\\"Type\\\":5,\\\"Path\\\":\\\"/PCFControls/PowerApps_CoreControls_LinkCanvas/strings/LinkCanvas.1062.json\\\",\\\"ModifiedPath\\\":\\\"\\\",\\\"LoadingOrder\\\":13,\\\"IsControlSpecific\\\":true},{\\\"Type\\\":5,\\\"Path\\\":\\\"/PCFControls/PowerApps_CoreControls_LinkCanvas/strings/LinkCanvas.1063.json\\\",\\\"ModifiedPath\\\":\\\"\\\",\\\"LoadingOrder\\\":13,\\\"IsControlSpecific\\\":true},{\\\"Type\\\":5,\\\"Path\\\":\\\"/PCFControls/PowerApps_CoreControls_LinkCanvas/strings/LinkCanvas.1066.json\\\",\\\"ModifiedPath\\\":\\\"\\\",\\\"LoadingOrder\\\":13,\\\"IsControlSpecific\\\":true},{\\\"Type\\\":5,\\\"Path\\\":\\\"/PCFControls/PowerApps_CoreControls_LinkCanvas/strings/LinkCanvas.1069.json\\\",\\\"ModifiedPath\\\":\\\"\\\",\\\"LoadingOrder\\\":13,\\\"IsControlSpecific\\\":true},{\\\"Type\\\":5,\\\"Path\\\":\\\"/PCFControls/PowerApps_CoreControls_LinkCanvas/strings/LinkCanvas.1081.json\\\",\\\"ModifiedPath\\\":\\\"\\\",\\\"LoadingOrder\\\":13,\\\"IsControlSpecific\\\":true},{\\\"Type\\\":5,\\\"Path\\\":\\\"/PCFControls/PowerApps_CoreControls_LinkCanvas/strings/LinkCanvas.1086.json\\\",\\\"ModifiedPath\\\":\\\"\\\",\\\"LoadingOrder\\\":13,\\\"IsControlSpecific\\\":true},{\\\"Type\\\":5,\\\"Path\\\":\\\"/PCFControls/PowerApps_CoreControls_LinkCanvas/strings/LinkCanvas.1087.json\\\",\\\"ModifiedPath\\\":\\\"\\\",\\\"LoadingOrder\\\":13,\\\"IsControlSpecific\\\":true},{\\\"Type\\\":5,\\\"Path\\\":\\\"/PCFControls/PowerApps_CoreControls_LinkCanvas/strings/LinkCanvas.1110.json\\\",\\\"ModifiedPath\\\":\\\"\\\",\\\"LoadingOrder\\\":13,\\\"IsControlSpecific\\\":true},{\\\"Type\\\":5,\\\"Path\\\":\\\"/PCFControls/PowerApps_CoreControls_LinkCanvas/strings/LinkCanvas.2052.json\\\",\\\"ModifiedPath\\\":\\\"\\\",\\\"LoadingOrder\\\":13,\\\"IsControlSpecific\\\":true},{\\\"Type\\\":5,\\\"Path\\\":\\\"/PCFControls/PowerApps_CoreControls_LinkCanvas/strings/LinkCanvas.2070.json\\\",\\\"ModifiedPath\\\":\\\"\\\",\\\"LoadingOrder\\\":13,\\\"IsControlSpecific\\\":true},{\\\"Type\\\":5,\\\"Path\\\":\\\"/PCFControls/PowerApps_CoreControls_LinkCanvas/strings/LinkCanvas.2074.json\\\",\\\"ModifiedPath\\\":\\\"\\\",\\\"LoadingOrder\\\":13,\\\"IsControlSpecific\\\":true},{\\\"Type\\\":5,\\\"Path\\\":\\\"/PCFControls/PowerApps_CoreControls_LinkCanvas/strings/LinkCanvas.3076.json\\\",\\\"ModifiedPath\\\":\\\"\\\",\\\"LoadingOrder\\\":13,\\\"IsControlSpecific\\\":true},{\\\"Type\\\":5,\\\"Path\\\":\\\"/PCFControls/PowerApps_CoreControls_LinkCanvas/strings/LinkCanvas.3082.json\\\",\\\"ModifiedPath\\\":\\\"\\\",\\\"LoadingOrder\\\":13,\\\"IsControlSpecific\\\":true},{\\\"Type\\\":5,\\\"Path\\\":\\\"/PCFControls/PowerApps_CoreControls_LinkCanvas/strings/LinkCanvas.3098.json\\\",\\\"ModifiedPath\\\":\\\"\\\",\\\"LoadingOrder\\\":13,\\\"IsControlSpecific\\\":true},{\\\"Type\\\":3,\\\"Path\\\":\\\"{\\\\\\\"Id\\\\\\\":\\\\\\\"LocalizedStrings\\\\\\\",\\\\\\\"Data\\\\\\\":{\\\\\\\"LocStrings\\\\\\\":{\\\\\\\"LinkCanvas\\\\\\\":\\\\\\\"Link\\\\\\\",\\\\\\\"LinkCanvas_AcceptsFocus\\\\\\\":\\\\\\\"Accepts focus\\\\\\\",\\\\\\\"LinkCanvas_AcceptsFocus_Desc\\\\\\\":\\\\\\\"Whether this field can be reached with Tab key.\\\\\\\",\\\\\\\"LinkCanvas_AccessibleLabel\\\\\\\":\\\\\\\"Accessible label\\\\\\\",\\\\\\\"LinkCanvas_AccessibleLabel_Desc\\\\\\\":\\\\\\\"Label read out by screen readers.\\\\\\\",\\\\\\\"LinkCanvas_Desc\\\\\\\":\\\\\\\"Let users navigate to a web page or a different screen.\\\\\\\",\\\\\\\"LinkCanvas_Text\\\\\\\":\\\\\\\"Text\\\\\\\",\\\\\\\"LinkCanvas_Text_Desc\\\\\\\":\\\\\\\"Set the text of of the link control.\\\\\\\",\\\\\\\"LinkCanvas_URL\\\\\\\":\\\\\\\"URL\\\\\\\",\\\\\\\"LinkCanvas_URL_Desc\\\\\\\":\\\\\\\"Website address to navigate to when the link is selected. Ignored when the control is used as a button through the As property.\\\\\\\"}}}\\\",\\\"ModifiedPath\\\":\\\"\\\",\\\"LoadingOrder\\\":13,\\\"IsControlSpecific\\\":false},{\\\"Type\\\":0,\\\"Path\\\":\\\"/PCF/fluentui-react.js\\\",\\\"ModifiedPath\\\":\\\"\\\",\\\"LoadingOrder\\\":5,\\\"IsControlSpecific\\\":false}]\",\"Properties\":\"[{\\\"Name\\\":\\\"AcceptsFocus\\\",\\\"DisplayName\\\":\\\"Accepts focus\\\",\\\"Description\\\":\\\"Whether this field can be reached with Tab key.\\\",\\\"Type\\\":20,\\\"Usage\\\":0,\\\"Hidden\\\":false,\\\"DefaultValue\\\":\\\"true\\\",\\\"PhoneDefaultValue\\\":\\\"\\\",\\\"WebDefaultValue\\\":\\\"\\\",\\\"NullDefaultValue\\\":null,\\\"HelperUI\\\":\\\"\\\",\\\"Category\\\":\\\"data\\\",\\\"IsPrimaryBehavioral\\\":false,\\\"IsPrimaryInput\\\":false,\\\"IsPrimaryOutput\\\":false,\\\"IsResettable\\\":false,\\\"EnumValues\\\":[],\\\"Required\\\":false,\\\"IsDataSourceProperty\\\":false,\\\"PassThroughProperty\\\":\\\"\\\",\\\"ShouldAutoBind\\\":false,\\\"ParentDataSetName\\\":\\\"\\\",\\\"DisplayNameResourceString\\\":\\\"LinkCanvas_AcceptsFocus\\\",\\\"DescriptionResourceString\\\":\\\"LinkCanvas_AcceptsFocus_Desc\\\"},{\\\"Name\\\":\\\"AccessibleLabel\\\",\\\"DisplayName\\\":\\\"Accessible label\\\",\\\"Description\\\":\\\"Label read out by screen readers.\\\",\\\"Type\\\":6,\\\"Usage\\\":0,\\\"Hidden\\\":false,\\\"DefaultValue\\\":\\\"Link\\\",\\\"PhoneDefaultValue\\\":\\\"\\\",\\\"WebDefaultValue\\\":\\\"\\\",\\\"NullDefaultValue\\\":null,\\\"HelperUI\\\":null,\\\"Category\\\":\\\"data\\\",\\\"IsPrimaryBehavioral\\\":false,\\\"IsPrimaryInput\\\":false,\\\"IsPrimaryOutput\\\":false,\\\"IsResettable\\\":false,\\\"EnumValues\\\":[],\\\"Required\\\":false,\\\"IsDataSourceProperty\\\":false,\\\"PassThroughProperty\\\":\\\"\\\",\\\"ShouldAutoBind\\\":false,\\\"ParentDataSetName\\\":\\\"\\\",\\\"DisplayNameResourceString\\\":\\\"LinkCanvas_AccessibleLabel\\\",\\\"DescriptionResourceString\\\":\\\"LinkCanvas_AccessibleLabel_Desc\\\"},{\\\"Name\\\":\\\"Text\\\",\\\"DisplayName\\\":\\\"Text\\\",\\\"Description\\\":\\\"Set the text of of the link control.\\\",\\\"Type\\\":6,\\\"Usage\\\":0,\\\"Hidden\\\":false,\\\"DefaultValue\\\":\\\"Link\\\",\\\"PhoneDefaultValue\\\":\\\"\\\",\\\"WebDefaultValue\\\":\\\"\\\",\\\"NullDefaultValue\\\":null,\\\"HelperUI\\\":null,\\\"Category\\\":\\\"data\\\",\\\"IsPrimaryBehavioral\\\":false,\\\"IsPrimaryInput\\\":false,\\\"IsPrimaryOutput\\\":false,\\\"IsResettable\\\":false,\\\"EnumValues\\\":[],\\\"Required\\\":false,\\\"IsDataSourceProperty\\\":false,\\\"PassThroughProperty\\\":\\\"\\\",\\\"ShouldAutoBind\\\":false,\\\"ParentDataSetName\\\":\\\"\\\",\\\"DisplayNameResourceString\\\":\\\"LinkCanvas_Text\\\",\\\"DescriptionResourceString\\\":\\\"LinkCanvas_Text_Desc\\\"},{\\\"Name\\\":\\\"URL\\\",\\\"DisplayName\\\":\\\"URL\\\",\\\"Description\\\":\\\"Website address to navigate to when the link is selected. Ignored when the control is used as a button through the As property.\\\",\\\"Type\\\":6,\\\"Usage\\\":0,\\\"Hidden\\\":false,\\\"DefaultValue\\\":\\\"\\\",\\\"PhoneDefaultValue\\\":\\\"\\\",\\\"WebDefaultValue\\\":\\\"\\\",\\\"NullDefaultValue\\\":null,\\\"HelperUI\\\":null,\\\"Category\\\":\\\"data\\\",\\\"IsPrimaryBehavioral\\\":false,\\\"IsPrimaryInput\\\":true,\\\"IsPrimaryOutput\\\":false,\\\"IsResettable\\\":false,\\\"EnumValues\\\":[],\\\"Required\\\":false,\\\"IsDataSourceProperty\\\":false,\\\"PassThroughProperty\\\":\\\"\\\",\\\"ShouldAutoBind\\\":false,\\\"ParentDataSetName\\\":\\\"\\\",\\\"DisplayNameResourceString\\\":\\\"LinkCanvas_URL\\\",\\\"DescriptionResourceString\\\":\\\"LinkCanvas_URL_Desc\\\"},{\\\"Name\\\":\\\"TabIndex\\\",\\\"DisplayName\\\":\\\"NA\\\",\\\"Description\\\":\\\"NA\\\",\\\"Type\\\":16,\\\"Usage\\\":0,\\\"Hidden\\\":true,\\\"DefaultValue\\\":\\\"\\\",\\\"PhoneDefaultValue\\\":\\\"\\\",\\\"WebDefaultValue\\\":\\\"\\\",\\\"NullDefaultValue\\\":null,\\\"HelperUI\\\":\\\"\\\",\\\"Category\\\":\\\"design\\\",\\\"IsPrimaryBehavioral\\\":false,\\\"IsPrimaryInput\\\":false,\\\"IsPrimaryOutput\\\":false,\\\"IsResettable\\\":false,\\\"EnumValues\\\":[],\\\"Required\\\":false,\\\"IsDataSourceProperty\\\":false,\\\"PassThroughProperty\\\":\\\"\\\",\\\"ShouldAutoBind\\\":false,\\\"ParentDataSetName\\\":\\\"\\\",\\\"DisplayNameResourceString\\\":\\\"NA\\\",\\\"DescriptionResourceString\\\":\\\"NA\\\"},{\\\"Name\\\":\\\"Tooltip\\\",\\\"DisplayName\\\":\\\"NA\\\",\\\"Description\\\":\\\"NA\\\",\\\"Type\\\":6,\\\"Usage\\\":0,\\\"Hidden\\\":true,\\\"DefaultValue\\\":\\\"\\\",\\\"PhoneDefaultValue\\\":\\\"\\\",\\\"WebDefaultValue\\\":\\\"\\\",\\\"NullDefaultValue\\\":null,\\\"HelperUI\\\":\\\"\\\",\\\"Category\\\":\\\"design\\\",\\\"IsPrimaryBehavioral\\\":false,\\\"IsPrimaryInput\\\":false,\\\"IsPrimaryOutput\\\":false,\\\"IsResettable\\\":false,\\\"EnumValues\\\":[],\\\"Required\\\":false,\\\"IsDataSourceProperty\\\":false,\\\"PassThroughProperty\\\":\\\"\\\",\\\"ShouldAutoBind\\\":false,\\\"ParentDataSetName\\\":\\\"\\\",\\\"DisplayNameResourceString\\\":\\\"NA\\\",\\\"DescriptionResourceString\\\":\\\"NA\\\"},{\\\"Name\\\":\\\"PCFTeamsTheme\\\",\\\"DisplayName\\\":\\\"PCFTeamsTheme\\\",\\\"Description\\\":\\\"\\\",\\\"Type\\\":3,\\\"Usage\\\":0,\\\"Hidden\\\":true,\\\"DefaultValue\\\":\\\"\\\",\\\"PhoneDefaultValue\\\":\\\"\\\",\\\"WebDefaultValue\\\":\\\"\\\",\\\"NullDefaultValue\\\":\\\"\\\",\\\"HelperUI\\\":\\\"\\\",\\\"Category\\\":\\\"design\\\",\\\"IsPrimaryBehavioral\\\":false,\\\"IsPrimaryInput\\\":false,\\\"IsPrimaryOutput\\\":false,\\\"IsResettable\\\":false,\\\"EnumValues\\\":null,\\\"Required\\\":false,\\\"IsDataSourceProperty\\\":false,\\\"PassThroughProperty\\\":\\\"\\\",\\\"ShouldAutoBind\\\":false,\\\"ParentDataSetName\\\":\\\"\\\",\\\"DisplayNameResourceString\\\":\\\"\\\",\\\"DescriptionResourceString\\\":\\\"\\\"}]\",\"IncludedProperties\":\"[{\\\"Name\\\":\\\"X\\\",\\\"DisplayName\\\":\\\"CC_X\\\",\\\"Description\\\":\\\"\\\",\\\"Type\\\":2,\\\"Usage\\\":2,\\\"Hidden\\\":false,\\\"DefaultValue\\\":\\\"\\\",\\\"PhoneDefaultValue\\\":\\\"\\\",\\\"WebDefaultValue\\\":\\\"\\\",\\\"NullDefaultValue\\\":\\\"\\\",\\\"HelperUI\\\":\\\"\\\",\\\"Category\\\":\\\"design\\\",\\\"IsPrimaryBehavioral\\\":false,\\\"IsPrimaryInput\\\":false,\\\"IsPrimaryOutput\\\":false,\\\"IsResettable\\\":false,\\\"EnumValues\\\":null,\\\"Required\\\":false,\\\"IsDataSourceProperty\\\":false,\\\"PassThroughProperty\\\":\\\"\\\",\\\"ShouldAutoBind\\\":false,\\\"ParentDataSetName\\\":\\\"\\\",\\\"DisplayNameResourceString\\\":\\\"CC_X\\\",\\\"DescriptionResourceString\\\":\\\"\\\"},{\\\"Name\\\":\\\"Y\\\",\\\"DisplayName\\\":\\\"CC_Y\\\",\\\"Description\\\":\\\"\\\",\\\"Type\\\":2,\\\"Usage\\\":2,\\\"Hidden\\\":false,\\\"DefaultValue\\\":\\\"\\\",\\\"PhoneDefaultValue\\\":\\\"\\\",\\\"WebDefaultValue\\\":\\\"\\\",\\\"NullDefaultValue\\\":\\\"\\\",\\\"HelperUI\\\":\\\"\\\",\\\"Category\\\":\\\"design\\\",\\\"IsPrimaryBehavioral\\\":false,\\\"IsPrimaryInput\\\":false,\\\"IsPrimaryOutput\\\":false,\\\"IsResettable\\\":false,\\\"EnumValues\\\":null,\\\"Required\\\":false,\\\"IsDataSourceProperty\\\":false,\\\"PassThroughProperty\\\":\\\"\\\",\\\"ShouldAutoBind\\\":false,\\\"ParentDataSetName\\\":\\\"\\\",\\\"DisplayNameResourceString\\\":\\\"CC_Y\\\",\\\"DescriptionResourceString\\\":\\\"\\\"},{\\\"Name\\\":\\\"Width\\\",\\\"DisplayName\\\":\\\"Width\\\",\\\"Description\\\":\\\"\\\",\\\"Type\\\":2,\\\"Usage\\\":2,\\\"Hidden\\\":false,\\\"DefaultValue\\\":\\\"320\\\",\\\"PhoneDefaultValue\\\":\\\"320\\\",\\\"WebDefaultValue\\\":\\\"320\\\",\\\"NullDefaultValue\\\":\\\"0\\\",\\\"HelperUI\\\":\\\"\\\",\\\"Category\\\":\\\"design\\\",\\\"IsPrimaryBehavioral\\\":false,\\\"IsPrimaryInput\\\":false,\\\"IsPrimaryOutput\\\":false,\\\"IsResettable\\\":false,\\\"EnumValues\\\":null,\\\"Required\\\":false,\\\"IsDataSourceProperty\\\":false,\\\"PassThroughProperty\\\":\\\"\\\",\\\"ShouldAutoBind\\\":false,\\\"ParentDataSetName\\\":\\\"\\\",\\\"DisplayNameResourceString\\\":\\\"Width\\\",\\\"DescriptionResourceString\\\":\\\"\\\"},{\\\"Name\\\":\\\"Height\\\",\\\"DisplayName\\\":\\\"Height\\\",\\\"Description\\\":\\\"\\\",\\\"Type\\\":2,\\\"Usage\\\":2,\\\"Hidden\\\":false,\\\"DefaultValue\\\":\\\"32\\\",\\\"PhoneDefaultValue\\\":\\\"32\\\",\\\"WebDefaultValue\\\":\\\"32\\\",\\\"NullDefaultValue\\\":\\\"0\\\",\\\"HelperUI\\\":\\\"\\\",\\\"Category\\\":\\\"design\\\",\\\"IsPrimaryBehavioral\\\":false,\\\"IsPrimaryInput\\\":false,\\\"IsPrimaryOutput\\\":false,\\\"IsResettable\\\":false,\\\"EnumValues\\\":null,\\\"Required\\\":false,\\\"IsDataSourceProperty\\\":false,\\\"PassThroughProperty\\\":\\\"\\\",\\\"ShouldAutoBind\\\":false,\\\"ParentDataSetName\\\":\\\"\\\",\\\"DisplayNameResourceString\\\":\\\"Height\\\",\\\"DescriptionResourceString\\\":\\\"\\\"},{\\\"Name\\\":\\\"Visible\\\",\\\"DisplayName\\\":\\\"Visible\\\",\\\"Description\\\":\\\"\\\",\\\"Type\\\":4,\\\"Usage\\\":2,\\\"Hidden\\\":false,\\\"DefaultValue\\\":\\\"true\\\",\\\"PhoneDefaultValue\\\":\\\"\\\",\\\"WebDefaultValue\\\":\\\"\\\",\\\"NullDefaultValue\\\":\\\"\\\",\\\"HelperUI\\\":\\\"\\\",\\\"Category\\\":\\\"design\\\",\\\"IsPrimaryBehavioral\\\":false,\\\"IsPrimaryInput\\\":false,\\\"IsPrimaryOutput\\\":false,\\\"IsResettable\\\":false,\\\"EnumValues\\\":null,\\\"Required\\\":false,\\\"IsDataSourceProperty\\\":false,\\\"PassThroughProperty\\\":\\\"\\\",\\\"ShouldAutoBind\\\":false,\\\"ParentDataSetName\\\":\\\"\\\",\\\"DisplayNameResourceString\\\":\\\"Visible\\\",\\\"DescriptionResourceString\\\":\\\"\\\"},{\\\"Name\\\":\\\"DisplayMode\\\",\\\"DisplayName\\\":\\\"DisplayMode\\\",\\\"Description\\\":\\\"\\\",\\\"Type\\\":27,\\\"Usage\\\":2,\\\"Hidden\\\":false,\\\"DefaultValue\\\":\\\"\\\",\\\"PhoneDefaultValue\\\":\\\"\\\",\\\"WebDefaultValue\\\":\\\"\\\",\\\"NullDefaultValue\\\":\\\"\\\",\\\"HelperUI\\\":\\\"\\\",\\\"Category\\\":\\\"design\\\",\\\"IsPrimaryBehavioral\\\":false,\\\"IsPrimaryInput\\\":false,\\\"IsPrimaryOutput\\\":false,\\\"IsResettable\\\":false,\\\"EnumValues\\\":null,\\\"Required\\\":false,\\\"IsDataSourceProperty\\\":false,\\\"PassThroughProperty\\\":\\\"\\\",\\\"ShouldAutoBind\\\":false,\\\"ParentDataSetName\\\":\\\"\\\",\\\"DisplayNameResourceString\\\":\\\"DisplayMode\\\",\\\"DescriptionResourceString\\\":\\\"\\\"}]\",\"CommonEvents\":\"[{\\\"Name\\\":\\\"OnChange\\\",\\\"DisplayName\\\":\\\"OnChange\\\",\\\"Description\\\":\\\"\\\",\\\"Hidden\\\":false,\\\"IsPrimaryInput\\\":false}]\",\"SubscribedFunctionalities\":\"{\\\"autoDisabledViewState\\\":\\\"true\\\",\\\"supportSetFocus\\\":\\\"true\\\"}\",\"AuthConfigProperties\":\"[{\\\"Text\\\":{\\\"SectionIndex\\\":0,\\\"HelperUI\\\":null,\\\"PropertyGroupName\\\":\\\"\\\",\\\"SectionName\\\":null,\\\"Type\\\":0,\\\"PropertyKind\\\":1,\\\"WizardStep\\\":null,\\\"EnabledForFlyout\\\":false,\\\"Hidden\\\":false},\\\"URL\\\":{\\\"SectionIndex\\\":0,\\\"HelperUI\\\":null,\\\"PropertyGroupName\\\":\\\"\\\",\\\"SectionName\\\":null,\\\"Type\\\":0,\\\"PropertyKind\\\":1,\\\"WizardStep\\\":null,\\\"EnabledForFlyout\\\":false,\\\"Hidden\\\":false},\\\"DisplayMode\\\":{\\\"SectionIndex\\\":1,\\\"HelperUI\\\":null,\\\"PropertyGroupName\\\":\\\"\\\",\\\"SectionName\\\":null,\\\"Type\\\":27,\\\"PropertyKind\\\":1,\\\"WizardStep\\\":null,\\\"EnabledForFlyout\\\":false,\\\"Hidden\\\":false},\\\"AccessibleLabel\\\":{\\\"SectionIndex\\\":1,\\\"HelperUI\\\":null,\\\"PropertyGroupName\\\":\\\"\\\",\\\"SectionName\\\":null,\\\"Type\\\":0,\\\"PropertyKind\\\":1,\\\"WizardStep\\\":null,\\\"EnabledForFlyout\\\":false,\\\"Hidden\\\":false},\\\"X\\\":{\\\"SectionIndex\\\":2,\\\"HelperUI\\\":null,\\\"PropertyGroupName\\\":\\\"Position\\\",\\\"SectionName\\\":null,\\\"Type\\\":0,\\\"PropertyKind\\\":2,\\\"WizardStep\\\":null,\\\"EnabledForFlyout\\\":false,\\\"Hidden\\\":false},\\\"Y\\\":{\\\"SectionIndex\\\":2,\\\"HelperUI\\\":null,\\\"PropertyGroupName\\\":\\\"Position\\\",\\\"SectionName\\\":null,\\\"Type\\\":0,\\\"PropertyKind\\\":2,\\\"WizardStep\\\":null,\\\"EnabledForFlyout\\\":false,\\\"Hidden\\\":false},\\\"Width\\\":{\\\"SectionIndex\\\":2,\\\"HelperUI\\\":null,\\\"PropertyGroupName\\\":\\\"Size\\\",\\\"SectionName\\\":null,\\\"Type\\\":0,\\\"PropertyKind\\\":2,\\\"WizardStep\\\":null,\\\"EnabledForFlyout\\\":false,\\\"Hidden\\\":false},\\\"Height\\\":{\\\"SectionIndex\\\":2,\\\"HelperUI\\\":null,\\\"PropertyGroupName\\\":\\\"Size\\\",\\\"SectionName\\\":null,\\\"Type\\\":0,\\\"PropertyKind\\\":2,\\\"WizardStep\\\":null,\\\"EnabledForFlyout\\\":false,\\\"Hidden\\\":false}}]\"}",
      "FirstParty": true,
      "Id": "http://microsoft.com/appmagic/powercontrol/PowerApps_CoreControls_LinkCanvas",
      "IsComponentDefinition": false,
      "IsCustomGroupControlTemplate": false,
      "IsPremiumPcfControl": false,
      "LastModifiedTimestamp": "0",
      "Name": "PowerApps_CoreControls_LinkCanvas",
      "OverridableProperties": {},
      "TemplateDisplayName": "Link",
      "Version": "0.0.12"
    }
  },
  "PublishOrderIndices": {
    "Actual ETA_DataCard1": 140,
    "Actual ETD_DataCard1": 130,
    "ActualETA_TD_6": 47,
    "ActualETD_TD_6": 46,
    "App": 0,
    "Approved Cases_DataCard1": 186,
    "AttachmentControl_2": 382,
    "AttachmentControl_4": 320,
    "BL#_DataCard1": 160,
    "BLNo_TD_6": 51,
    "BU Comment_DataCard1": 201,
    "button_approve": 285,
    "Button_CancelGoBack": 286,
    "Button_CancelGoBack_2": 298,
    "Button_CIN_TD_3": 37,
    "Button_delete": 284,
    "button_gallery_cin_2": 404,
    "button_gallery_cin_4": 478,
    "button_gallery_cin_5": 353,
    "button_process": 288,
    "Button_reject": 287,
    "Button_reject_2": 297,
    "button_Submit": 283,
    "Button2_2": 384,
    "Button2_4": 324,
    "Button5": 495,
    "CancelUpload": 275,
    "Canvas2_1": 462,
    "cbKPI_ClaimType": 459,
    "cbKPI_Market": 460,
    "cbKPI_Period": 461,
    "CIN (Title)_DataCard1": 78,
    "Claim Status_DataCard1": 115,
    "Claim Type_DataCard1": 135,
    "claim_draft_screen": 37,
    "ClaimForm": 77,
    "ClaimSubDate_TD_6": 55,
    "ClaimType_TD_6": 38,
    "ColumnChart1": 429,
    "ColumnChart2_2": 325,
    "combo_ct_2": 389,
    "combo_ct_7": 313,
    "combo_ct_8": 333,
    "combo_market_3": 315,
    "combo_status_2": 390,
    "combo_status_6": 314,
    "combo_status_7": 334,
    "CompositeColumnChart1": 424,
    "CompositeLineChart1": 425,
    "CompositePieChart1": 426,
    "cont_Attachment": 258,
    "cont_ClaimDetail": 72,
    "cont_PopupGrey": 73,
    "Container #_DataCard1": 155,
    "Container1": 455,
    "Container1_2": 378,
    "Container1_5": 309,
    "Container1_8": 10,
    "Container2": 439,
    "Container3": 440,
    "Container4": 335,
    "Container5": 441,
    "Container7_1": 336,
    "ContainerErrorETA": 247,
    "ContainerErrorKelloggPO": 241,
    "ContainerErrorSSCC": 244,
    "ContainerNo_TD_6": 50,
    "CusReqETA_TD_6": 45,
    "Customer Comment_DataCard1": 196,
    "Customer PO_DataCard1": 83,
    "Customer Requested ETA_DataCard1": 125,
    "CustomerPO_TD_6": 39,
    "dashboard_btn_10": 449,
    "dashboard_btn_11": 4,
    "dashboard_btn_3": 372,
    "dashboard_btn_5": 303,
    "dashboard_btn_7": 65,
    "DataCard2_1": 463,
    "DataCardKey1": 80,
    "DataCardKey10": 127,
    "DataCardKey11": 132,
    "DataCardKey12": 142,
    "DataCardKey13": 147,
    "DataCardKey14": 152,
    "DataCardKey15": 157,
    "DataCardKey16": 162,
    "DataCardKey17": 167,
    "DataCardKey18": 183,
    "DataCardKey19": 178,
    "DataCardKey2": 101,
    "DataCardKey20": 117,
    "DataCardKey21": 188,
    "DataCardKey22": 198,
    "DataCardKey23": 203,
    "DataCardKey24": 208,
    "DataCardKey25": 213,
    "DataCardKey26": 218,
    "DataCardKey27": 173,
    "DataCardKey28": 193,
    "DataCardKey3": 137,
    "DataCardKey4": 85,
    "DataCardKey5": 90,
    "DataCardKey6": 95,
    "DataCardKey7": 107,
    "DataCardKey8": 112,
    "DataCardKey9": 122,
    "DataCardValue1": 81,
    "DataCardValue10": 128,
    "DataCardValue11": 133,
    "DataCardValue12": 143,
    "DataCardValue13": 148,
    "DataCardValue14": 153,
    "DataCardValue15": 158,
    "DataCardValue16": 163,
    "DataCardValue17": 169,
    "DataCardValue18": 184,
    "DataCardValue19": 179,
    "DataCardValue2": 103,
    "DataCardValue20": 118,
    "DataCardValue21": 189,
    "DataCardValue22": 199,
    "DataCardValue23": 204,
    "DataCardValue24": 209,
    "DataCardValue25": 214,
    "DataCardValue26": 219,
    "DataCardValue27": 174,
    "DataCardValue28": 194,
    "DataCardValue3": 138,
    "DataCardValue4": 86,
    "DataCardValue5": 91,
    "DataCardValue6": 97,
    "DataCardValue7": 108,
    "DataCardValue8": 113,
    "DataCardValue9": 123,
    "DateBU": 517,
    "DateBU_1": 236,
    "DateGBS": 521,
    "DateGBS_1": 240,
    "DateNew": 519,
    "DateNew_1": 238,
    "DatePIOFinance": 520,
    "DatePIOFinance_1": 239,
    "DatePIOSPOC": 518,
    "DatePIOSPOC_1": 237,
    "dd__2": 383,
    "dd__4": 321,
    "DDRF#_DataCard1": 176,
    "DDRF_TD_6": 54,
    "draft_btn_11": 5,
    "draft_btn_3": 373,
    "draft_btn_7": 66,
    "draft_btn_9": 447,
    "draftclaimdetail_screen": 99,
    "ErrorETA": 249,
    "ErrorKelloggPO": 243,
    "ErrorMessage1": 82,
    "ErrorMessage10": 129,
    "ErrorMessage11": 134,
    "ErrorMessage12": 144,
    "ErrorMessage13": 149,
    "ErrorMessage14": 154,
    "ErrorMessage15": 159,
    "ErrorMessage16": 164,
    "ErrorMessage17": 170,
    "ErrorMessage18": 185,
    "ErrorMessage19": 180,
    "ErrorMessage2": 205,
    "ErrorMessage20": 119,
    "ErrorMessage21": 190,
    "ErrorMessage22": 200,
    "ErrorMessage23": 210,
    "ErrorMessage24": 215,
    "ErrorMessage25": 220,
    "ErrorMessage26": 175,
    "ErrorMessage27": 195,
    "ErrorMessage28": 104,
    "ErrorMessage3": 139,
    "ErrorMessage4": 87,
    "ErrorMessage5": 92,
    "ErrorMessage6": 98,
    "ErrorMessage7": 109,
    "ErrorMessage8": 114,
    "ErrorMessage9": 124,
    "ErrorSSCC": 246,
    "Estimated Claim Value_DataCard1": 171,
    "ExportToExcel_button": 327,
    "FileAttachment": 261,
    "Final Claim Value_DataCard1": 191,
    "FooterContainer1": 443,
    "forgot_pswrd": 420,
    "Gallery_CreditNote": 278,
    "Gallery_DamageImage": 262,
    "Gallery_Supporting Documents": 269,
    "Gallery_WHReceipt": 252,
    "Gallery4_3": 401,
    "Gallery4_6": 350,
    "GalleryKPI": 476,
    "galleryTemplate1": 492,
    "galleryTemplate2": 494,
    "galleryTemplate3": 253,
    "galleryTemplate3_2": 263,
    "galleryTemplate3_3": 270,
    "galleryTemplate3_6": 279,
    "galleryTemplate4_3": 402,
    "galleryTemplate4_5": 477,
    "galleryTemplate4_6": 351,
    "galleryTemplate4_9": 36,
    "GBS Comment_DataCard1": 216,
    "Group1_4": 316,
    "Group3_2": 380,
    "Group3_5": 318,
    "Group4": 329,
    "Group5": 338,
    "HeaderClaimDraft_6": 14,
    "HeaderContainer1_2": 62,
    "HeaderContainer1_5": 369,
    "HeaderContainer1_6": 445,
    "HeaderContainer1_7": 300,
    "HeaderContainer1_9": 1,
    "HeaderContainer2": 436,
    "HeightSubmenu": 499,
    "HorizontalMenuComponent": 1,
    "HorizontalMenuComponent_1": 423,
    "HorizontalMenuComponent_2": 437,
    "Icon_Add_ImageDamage": 259,
    "Icon_Add_SupportingDocs": 267,
    "Icon_AddCreditNote": 276,
    "Icon_AddWHReceipt": 250,
    "Icon1_2": 413,
    "Icon1_4": 365,
    "Icon1_6": 57,
    "Icon10": 497,
    "Icon11": 498,
    "Icon2_5": 59,
    "Icon2_7": 485,
    "Icon3": 76,
    "Icon4_1": 96,
    "Icon4_2": 168,
    "Icon4_4": 102,
    "Icon5": 293,
    "Icon5_10": 453,
    "Icon5_11": 307,
    "Icon5_5": 376,
    "Icon5_6": 70,
    "Icon5_8": 8,
    "Icon6_3": 7,
    "Icon6_5": 375,
    "Icon6_6": 69,
    "Icon6_8": 452,
    "Icon6_9": 306,
    "Icon7_1": 501,
    "Icon7_2": 502,
    "Icon8": 255,
    "Icon8_1": 265,
    "Icon8_2": 272,
    "Icon8_6": 281,
    "Icon9": 256,
    "Icon9_1": 266,
    "Icon9_2": 273,
    "Icon9_6": 282,
    "IconErrorETA": 248,
    "IconErrorKelloggPO": 242,
    "IconErrorSSCC": 245,
    "Image1": 417,
    "Image2_10": 446,
    "Image2_12": 2,
    "Image2_3": 370,
    "Image2_5": 301,
    "Image2_8": 63,
    "Image3_2": 381,
    "Image3_4": 319,
    "input_search_2": 388,
    "input_search_4": 332,
    "InvDate_TD_6": 49,
    "Invoice Date_DataCard1": 150,
    "Kellogg Code_DataCard1": 105,
    "Kellogg Inv #_DataCard1": 145,
    "Kellogg PO#_DataCard1": 93,
    "Kellogg SO#_DataCard1": 88,
    "KelloggCode_TD_6": 42,
    "KelloggInvNo_TD_6": 48,
    "KelloggPO_TD_6": 41,
    "KelloggSO_TD_6": 40,
    "kpi_btn_1": 304,
    "kpi_btn_2": 67,
    "kpi_btn_5": 450,
    "kpi_screen": 337,
    "Label_ActualETA_6": 25,
    "Label_ActualETD_6": 24,
    "Label_BLNo_6": 29,
    "Label_CIN_6": 15,
    "Label_ClaimSubDate_6": 33,
    "Label_ClaimType_6": 16,
    "Label_ContainerNo_6": 28,
    "Label_CusReqETA_6": 23,
    "Label_CustomerPO_6": 17,
    "Label_DDRF_6": 32,
    "Label_InvDate_6": 27,
    "Label_KelloggCode_6": 20,
    "Label_KelloggInvNo_6": 26,
    "Label_KelloggPO_6": 19,
    "Label_KelloggSO_6": 18,
    "Label_ProductDesc_6": 21,
    "Label_Quantity_6": 22,
    "Label_SSCCNo_6": 30,
    "Label_Status_6": 34,
    "Label_TotalCases_6": 31,
    "Label1": 294,
    "Label1_27": 391,
    "Label1_28": 392,
    "Label1_29": 393,
    "Label1_30": 394,
    "Label1_31": 395,
    "Label1_32": 396,
    "Label1_33": 397,
    "Label1_34": 398,
    "Label1_35": 399,
    "Label1_42": 470,
    "Label1_43": 471,
    "Label1_44": 472,
    "Label1_45": 473,
    "Label1_46": 474,
    "Label1_47": 475,
    "Label1_84": 337,
    "Label1_85": 339,
    "Label1_86": 340,
    "Label1_87": 341,
    "Label1_88": 342,
    "Label1_89": 343,
    "Label1_90": 344,
    "Label1_91": 345,
    "Label1_92": 346,
    "Label1_93": 347,
    "Label1_94": 348,
    "Label1_95": 349,
    "Label2": 291,
    "Label3_2": 400,
    "Label3_5": 366,
    "Label4": 74,
    "Label5": 254,
    "Label5_11": 374,
    "Label5_12": 280,
    "Label5_13": 68,
    "Label5_15": 6,
    "Label5_17": 305,
    "Label5_20": 451,
    "Label5_5": 264,
    "Label5_6": 271,
    "Label6": 251,
    "Label6_1": 260,
    "Label6_2": 268,
    "Label6_6": 277,
    "Label7_4": 323,
    "Label7_5": 322,
    "Label9_6": 11,
    "landing_screen": 380,
    "landing_screen_distributor": 450,
    "lbl_ClaimType1_11": 310,
    "lbl_ClaimType1_12": 330,
    "lbl_ClaimType1_6": 386,
    "lbl_ClaimType1_8": 456,
    "lbl_ClaimType2_2": 379,
    "lbl_ClaimType2_4": 317,
    "lbl_ecv": 359,
    "lbl_faq": 358,
    "lbl_fcv": 360,
    "lbl_hdn_warnings_2": 412,
    "lbl_hdn_warnings_4": 58,
    "lbl_hdn_warnings_5": 364,
    "lbl_hdn_warnings_7": 484,
    "lbl_SearchKeyword_6": 385,
    "lbl_SearchKeyword_8": 328,
    "lbl_Status_13": 311,
    "lbl_Status_14": 312,
    "lbl_Status_15": 331,
    "lbl_Status_6": 387,
    "lbl_Status_8": 457,
    "lbl_Status_9": 458,
    "lbl_tbl_cd_2": 409,
    "lbl_tbl_cd_4": 361,
    "lbl_tbl_comments_2": 411,
    "lbl_tbl_comments_4": 363,
    "lbl_tbl_country_2": 403,
    "lbl_tbl_country_4": 479,
    "lbl_tbl_country_5": 352,
    "lbl_tbl_ct_2": 405,
    "lbl_tbl_ct_4": 480,
    "lbl_tbl_ct_5": 354,
    "lbl_tbl_in_2": 407,
    "lbl_tbl_in_4": 482,
    "lbl_tbl_in_5": 356,
    "lbl_tbl_kpo_2": 406,
    "lbl_tbl_kpo_4": 481,
    "lbl_tbl_kpo_5": 355,
    "lbl_tbl_status_2": 410,
    "lbl_tbl_status_4": 362,
    "lbl_tbl_tcfc_2": 408,
    "lbl_tbl_tcfc_4": 483,
    "lbl_tbl_tcfc_5": 357,
    "Legend3": 434,
    "LineChart1": 430,
    "LineChart2_2": 326,
    "LinkCanvas1": 257,
    "login_btn": 422,
    "login_screen": 498,
    "Logo": 490,
    "MainMenu": 491,
    "MainSectionContainer1_2": 71,
    "MainSectionContainer1_5": 377,
    "MainSectionContainer1_6": 454,
    "MainSectionContainer1_7": 308,
    "MainSectionContainer1_9": 9,
    "MainSectionContainer2": 438,
    "menu_screen": 507,
    "password_txt": 419,
    "PieChart1": 433,
    "PIOFinance Comment_DataCard1": 211,
    "PIOSPOC Comment_DataCard1": 206,
    "PopupReject": 290,
    "PowerBI1": 432,
    "PowerBI12": 464,
    "PowerBI13": 465,
    "PowerBI14": 466,
    "PowerBI15": 467,
    "PowerBI16": 468,
    "PowerBI18": 469,
    "Product Description _DataCard1": 110,
    "ProductDes_TD_6": 43,
    "Progress_Trail": 221,
    "ProgressBar": 16,
    "ProgressBar_1": 442,
    "Quantity (cs)_DataCard1": 120,
    "Quantity_TD_6": 44,
    "Rectangle1": 415,
    "Rectangle2": 416,
    "Rectangle3": 75,
    "Rectangle4": 489,
    "Rectangle5": 496,
    "Rectangle6": 367,
    "Rectangle6_10": 229,
    "Rectangle6_11": 230,
    "Rectangle6_2": 414,
    "Rectangle6_3": 60,
    "Rectangle6_4": 508,
    "Rectangle6_5": 509,
    "Rectangle6_6": 510,
    "Rectangle6_7": 511,
    "Rectangle6_8": 227,
    "Rectangle6_9": 228,
    "Rectangle7_10": 448,
    "Rectangle7_11": 3,
    "Rectangle7_3": 371,
    "Rectangle7_5": 302,
    "Rectangle7_7": 64,
    "RectangleOverlay": 289,
    "RectangleRejectReasonPopup": 292,
    "RejectReason": 295,
    "RejectReasonOthers": 296,
    "remember_cb": 421,
    "SaveDocument": 274,
    "ScreenContainer1_10": 0,
    "ScreenContainer1_2": 61,
    "ScreenContainer1_5": 368,
    "ScreenContainer1_6": 444,
    "ScreenContainer1_7": 299,
    "ScreenContainer2": 435,
    "SearchInput_6": 12,
    "SSCC#_DataCard1": 165,
    "SSCC_TD_6": 52,
    "StarVisible1": 79,
    "StarVisible10": 126,
    "StarVisible11": 131,
    "StarVisible12": 141,
    "StarVisible13": 146,
    "StarVisible14": 151,
    "StarVisible15": 156,
    "StarVisible16": 161,
    "StarVisible17": 166,
    "StarVisible18": 182,
    "StarVisible19": 177,
    "StarVisible2": 202,
    "StarVisible20": 116,
    "StarVisible21": 187,
    "StarVisible22": 197,
    "StarVisible23": 207,
    "StarVisible24": 212,
    "StarVisible25": 217,
    "StarVisible26": 172,
    "StarVisible27": 192,
    "StarVisible28": 100,
    "StarVisible3": 136,
    "StarVisible4": 84,
    "StarVisible5": 89,
    "StarVisible6": 94,
    "StarVisible7": 106,
    "StarVisible8": 111,
    "StarVisible9": 121,
    "status_screen": 524,
    "Status_TD_6": 56,
    "StatusIcon_10": 225,
    "StatusIcon_11": 226,
    "StatusIcon_2": 503,
    "StatusIcon_3": 504,
    "StatusIcon_4": 505,
    "StatusIcon_5": 506,
    "StatusIcon_6": 507,
    "StatusIcon_7": 222,
    "StatusIcon_8": 223,
    "StatusIcon_9": 224,
    "Submenu": 493,
    "Submission Date_DataCard1": 99,
    "TableClaimDraft_6": 13,
    "TableDataClaimDraft_6": 35,
    "Title1": 427,
    "Title2": 428,
    "Title3": 431,
    "Title4_10": 234,
    "Title4_11": 235,
    "Title4_2": 512,
    "Title4_3": 513,
    "Title4_4": 514,
    "Title4_5": 515,
    "Title4_6": 516,
    "Title4_7": 231,
    "Title4_8": 232,
    "Title4_9": 233,
    "Total cases for Claim_DataCard1": 181,
    "TotalCases_TD_6": 53,
    "username": 500,
    "username_txt": 418
  },
  "ResourcesJsonIndices": {
    "Image-Kelloggs_login": 2,
    "Image-Kellogs.KelloggLogo650x366": 3,
    "Image-SampleImage": 0,
    "Pdf-SamplePdf": 1
  },
  "RuleScreenIdWithoutScreen": {},
  "TemplateVersions": {},
  "VolatileProperties": {
    "AnalysisLoadTime": 2.8202591,
    "ControlCount": {
      "028175e180d7486f9f0c28262b40d618": 2,
      "addMedia": 1,
      "attachments": 3,
      "barChart": 2,
      "button": 31,
      "checkbox": 1,
      "combobox": 12,
      "dataCard": 1,
      "datepicker": 5,
      "dropdown": 3,
      "edba5150e0cb4e3bb0532a7de693516b": 3,
      "fluidGrid": 1,
      "form": 1,
      "gallery": 10,
      "galleryTemplate": 10,
      "group": 10,
      "groupContainer": 35,
      "icon": 49,
      "image": 10,
      "label": 242,
      "legend": 1,
      "lineChart": 2,
      "pieChart": 1,
      "powerbi": 7,
      "rectangle": 25,
      "screen": 9,
      "text": 27,
      "typedDataCard": 28
    },
    "DeserializationLoadTime": 4.1750044,
    "ErrorCount": 201
  },
  "WasLocalDatabaseReferencesEmpty": true
}