{
  "ComponentIndexes": {},
  "ControlUniqueGuids": {},
  "ControlUniqueIds": {
    "App": 1,
    "dashboard_btn": 17,
    "FooterContainer1": 29,
    "forgot_pswrd": 9,
    "Gallery1": 22,
    "galleryTemplate1": 23,
    "HeaderContainer1": 14,
    "Image1": 6,
    "Image2": 15,
    "Image3": 24,
    "Import1": 21,
    "Label5": 18,
    "landing_screen": 12,
    "login_btn": 11,
    "login_screen": 3,
    "logout_btn": 19,
    "MainSectionContainer1": 20,
    "NextArrow1": 26,
    "password_txt": 8,
    "Rectangle1": 4,
    "Rectangle2": 5,
    "Rectangle7": 16,
    "remember_cb": 10,
    "ScreenContainer1": 13,
    "Separator1": 28,
    "Subtitle1": 27,
    "Title1": 25,
    "username_txt": 7
  },
  "FunctionParamsInvariantScripts": {},
  "FunctionParamsInvariantScriptsOnInstances": {},
  "HeaderLastSavedDateTimeUTC": "03/28/2023 03:05:54",
  "IsLegacyComponentAllowGlobalScopeCase": false,
  "LocalConnectionIDReferences": {
    "2dbd8dad-6f1c-4c9b-9fae-345aa92406b2": "\"/providers/microsoft.powerapps/apis/shared_sharepointonline/connections/d1412dd66e0e44e98fef9b181e22e883\""
  },
  "LocalDatabaseReferencesAsEmpty": false,
  "LocalResourceFileNames": {
    "Kelloggs_login": "2e810758-1a31-4bdb-b479-c140ab096f5c.JPG",
    "Kellogs.KelloggLogo650x366": "9c0b5377-f10a-4cc1-a342-9cc51d90d394.png"
  },
  "LocalResourceRootPaths": {
    "Kelloggs_login": "https://docserverpwaprodweu.blob.core.windows.net/b5e75197-aeea-49d8-8274-ae0d6a76d739-1/resource/Assets0Images02e810758-1a31-4bdb-b479-c140ab096f5c.JPG?sv=2018-03-28&sr=b&sig=xUSKL3okOBaa3l6woVHG0Kz2anNZMXplgpHRdUYH%2BLE%3D&spr=https&se=2023-03-29T03%3A09%3A48Z&sp=r",
    "Kellogs.KelloggLogo650x366": "https://docserverpwaprodweu.blob.core.windows.net/b5e75197-aeea-49d8-8274-ae0d6a76d739-1/resource/Assets0Images09c0b5377-f10a-4cc1-a342-9cc51d90d394.png?sv=2018-03-28&sr=b&sig=u2U2sMGes4S8zpGwqWWVNj54rEWq6gkTBxh2pUhKP4s%3D&spr=https&se=2023-03-29T03%3A09%3A48Z&sp=r"
  },
  "OrderComponentMetadata": {},
  "OrderComponentTemplate": {},
  "OrderDataSource": {
    "claims": 1,
    "CustomGallerySample": 2,
    "users": 0
  },
  "OrderGroupControls": {},
  "OrderPcfTemplate": {},
  "OrderTemplate": {},
  "OrderXMLTemplate": {
    "button": 5,
    "checkbox": 4,
    "gallery": 8,
    "groupContainer": 6,
    "icon": 9,
    "image": 1,
    "import": 7,
    "label": 3,
    "rectangle": 0,
    "text": 2
  },
  "OverridablePropertiesEntry": {
    "App": {},
    "dashboard_btn": {},
    "FooterContainer1": {},
    "forgot_pswrd": {},
    "Gallery1": {},
    "galleryTemplate1": {},
    "HeaderContainer1": {},
    "Image1": {},
    "Image2": {},
    "Image3": {},
    "Import1": {
      "Data": {
        "Type": {
          "EnumString": "",
          "Kind": "Table",
          "Name": "Root",
          "Type": []
        },
        "Version": "1.330"
      }
    },
    "Label5": {},
    "landing_screen": {},
    "login_btn": {},
    "login_screen": {},
    "logout_btn": {},
    "MainSectionContainer1": {},
    "NextArrow1": {},
    "password_txt": {},
    "Rectangle1": {},
    "Rectangle2": {},
    "Rectangle7": {},
    "remember_cb": {},
    "ScreenContainer1": {},
    "Separator1": {},
    "Subtitle1": {},
    "Title1": {},
    "username_txt": {}
  },
  "PCFDynamicSchemaForIRRetrievalEntry": {
    "Import1": {}
  },
  "PCFTemplateEntry": {},
  "PublishOrderIndices": {
    "App": 0,
    "dashboard_btn": 12,
    "FooterContainer1": 24,
    "forgot_pswrd": 5,
    "Gallery1": 17,
    "galleryTemplate1": 18,
    "HeaderContainer1": 9,
    "Image1": 2,
    "Image2": 10,
    "Image3": 19,
    "Import1": 16,
    "Label5": 13,
    "landing_screen": 0,
    "login_btn": 7,
    "login_screen": 0,
    "logout_btn": 14,
    "MainSectionContainer1": 15,
    "NextArrow1": 21,
    "password_txt": 4,
    "Rectangle1": 0,
    "Rectangle2": 1,
    "Rectangle7": 11,
    "remember_cb": 6,
    "ScreenContainer1": 8,
    "Separator1": 23,
    "Subtitle1": 22,
    "Title1": 20,
    "username_txt": 3
  },
  "ResourcesJsonIndices": {
    "Image-Kelloggs_login": 1,
    "Image-Kellogs.KelloggLogo650x366": 2,
    "Image-SampleImage": 0
  },
  "RuleScreenIdWithoutScreen": {},
  "TemplateVersions": {},
  "VolatileProperties": {
    "AnalysisLoadTime": 0.163958,
    "ControlCount": {
      "button": 3,
      "checkbox": 1,
      "gallery": 1,
      "galleryTemplate": 1,
      "groupContainer": 4,
      "icon": 1,
      "image": 3,
      "import": 1,
      "label": 4,
      "rectangle": 4,
      "screen": 2,
      "text": 2
    },
    "DeserializationLoadTime": 1.0260507,
    "ErrorCount": 0
  },
  "WasLocalDatabaseReferencesEmpty": true
}